airflow/__init__.py
airflow/__main__.py
airflow/alembic.ini
airflow/configuration.py
airflow/customized_form_field_behaviours.schema.json
airflow/exceptions.py
airflow/git_version
airflow/logging_config.py
airflow/plugins_manager.py
airflow/provider_info.schema.json
airflow/providers_manager.py
airflow/py.typed
airflow/sentry.py
airflow/settings.py
airflow/stats.py
airflow/templates.py
airflow/typing_compat.py
airflow/version.py
airflow/_vendor/__init__.py
airflow/api/__init__.py
airflow/api/auth/__init__.py
airflow/api/auth/backend/__init__.py
airflow/api/auth/backend/basic_auth.py
airflow/api/auth/backend/default.py
airflow/api/auth/backend/deny_all.py
airflow/api/auth/backend/kerberos_auth.py
airflow/api/client/__init__.py
airflow/api/client/api_client.py
airflow/api/client/json_client.py
airflow/api/client/local_client.py
airflow/api/common/__init__.py
airflow/api/common/delete_dag.py
airflow/api/common/trigger_dag.py
airflow/api/common/experimental/__init__.py
airflow/api/common/experimental/delete_dag.py
airflow/api/common/experimental/get_code.py
airflow/api/common/experimental/get_dag_run_state.py
airflow/api/common/experimental/get_dag_runs.py
airflow/api/common/experimental/get_lineage.py
airflow/api/common/experimental/get_task.py
airflow/api/common/experimental/get_task_instance.py
airflow/api/common/experimental/mark_tasks.py
airflow/api/common/experimental/pool.py
airflow/api/common/experimental/trigger_dag.py
airflow/api_connexion/__init__.py
airflow/api_connexion/exceptions.py
airflow/api_connexion/parameters.py
airflow/api_connexion/security.py
airflow/api_connexion/endpoints/__init__.py
airflow/api_connexion/endpoints/config_endpoint.py
airflow/api_connexion/endpoints/connection_endpoint.py
airflow/api_connexion/endpoints/dag_endpoint.py
airflow/api_connexion/endpoints/dag_run_endpoint.py
airflow/api_connexion/endpoints/dag_source_endpoint.py
airflow/api_connexion/endpoints/event_log_endpoint.py
custom_workflow_solutions-2.2.5.dist-info/LICENSE
custom_workflow_solutions-2.2.5.dist-info/METADATA
custom_workflow_solutions-2.2.5.dist-info/NOTICE
custom_workflow_solutions-2.2.5.dist-info/WHEEL
custom_workflow_solutions-2.2.5.dist-info/entry_points.txt
custom_workflow_solutions-2.2.5.dist-info/top_level.txt
custom_workflow_solutions-2.2.5.dist-info/RECORD
