Metadata-Version: 2.1
Name: custom-workflow-solutions
Version: 2.2.5
Summary: Programmatically author, schedule and monitor data pipelines
Home-page: https://custom.workflow.com/
Author: Custom Foundation
Author-email: email@example.com
License: MIT
Download-URL: https://archive.apache.org/dist/airflow/2.2.5
Platform: UNKNOWN
Classifier: Development Status :: 5 - Production/Stable
Classifier: Environment :: Console
Classifier: Environment :: Web Environment
Classifier: Intended Audience :: Developers
Classifier: Intended Audience :: System Administrators
Classifier: License :: OSI Approved :: Apache Software License
Classifier: Programming Language :: Python :: 3.6
Classifier: Programming Language :: Python :: 3.7
Classifier: Programming Language :: Python :: 3.8
Classifier: Programming Language :: Python :: 3.9
Classifier: Topic :: System :: Monitoring
Requires-Python: ~=3.6
Requires-Dist: alembic (<2.0,>=1.5.1)
Requires-Dist: argcomplete (<3.0,>=1.10)
Requires-Dist: attrs (<21.0,>=20.0)
Requires-Dist: blinker
Requires-Dist: clickclick (>=1.2)
Requires-Dist: colorlog (<7.0,>=4.0.2)
Requires-Dist: connexion[flask,swagger-ui] (>=2.10.0)
Requires-Dist: croniter (>=0.3.17)
Requires-Dist: cryptography (>=0.9.3)
Requires-Dist: deprecated (>=1.2.13)
Requires-Dist: dill (<0.4,>=0.2.2)
Requires-Dist: docutils (<0.17)
Requires-Dist: flask (<2.0,>=1.1.0)
Requires-Dist: flask-appbuilder (==3.4.5)
Requires-Dist: flask-caching (<2.0.0,>=1.5.0)
Requires-Dist: flask-login (<0.5,>=0.3)
Requires-Dist: flask-session (<=0.4.0,>=0.3.1)
Requires-Dist: flask-wtf (<0.15,>=0.14.3)
Requires-Dist: graphviz (>=0.12)
Requires-Dist: gunicorn (>=20.1.0)
Requires-Dist: httpx
Requires-Dist: iso8601 (>=0.1.12)
Requires-Dist: itsdangerous (<2.0,>=1.1.0)
Requires-Dist: jinja2 (<3.1,>=2.10.1)
Requires-Dist: jsonschema (~=3.0)
Requires-Dist: lazy-object-proxy
Requires-Dist: lockfile (>=0.12.2)
Requires-Dist: markdown (<4.0,>=2.5.2)
Requires-Dist: markupsafe (<2.1.0,>=1.1.1)
Requires-Dist: marshmallow-oneofschema (>=2.0.1)
Requires-Dist: packaging (>=14.0)
Requires-Dist: pendulum (~=2.0)
Requires-Dist: psutil (<6.0.0,>=4.2.0)
Requires-Dist: pygments (<3.0,>=2.0.1)
Requires-Dist: pyjwt (<3)
Requires-Dist: python-daemon (>=2.2.4)
Requires-Dist: python-dateutil (<3,>=2.3)
Requires-Dist: python-nvd3 (~=0.15.0)
Requires-Dist: python-slugify (<5.0,>=3.0.0)
Requires-Dist: python3-openid (~=3.2)
Requires-Dist: rich (>=9.2.0)
Requires-Dist: setproctitle (<2,>=1.1.8)
Requires-Dist: sqlalchemy (<1.4.0,>=1.3.18)
Requires-Dist: sqlalchemy-jsonfield (~=1.0)
Requires-Dist: tabulate (<0.9,>=0.7.5)
Requires-Dist: tenacity (>=6.2.0)
Requires-Dist: termcolor (>=1.1.0)
Requires-Dist: typing-extensions (>=3.7.4)
Requires-Dist: unicodecsv (>=0.14.1)
Requires-Dist: werkzeug (>=1.0.1,~=1.0)
Requires-Dist: wtforms (<3.0.0)
Requires-Dist: apache-airflow-providers-ftp
Requires-Dist: apache-airflow-providers-http
Requires-Dist: apache-airflow-providers-imap
Requires-Dist: apache-airflow-providers-sqlite
Requires-Dist: dataclasses ; python_version < "3.7"
Requires-Dist: pep562 (~=1.0) ; python_version < "3.7"
Requires-Dist: importlib-metadata (>=1.7) ; python_version < "3.9"
Requires-Dist: importlib-resources (~=5.2) ; python_version < "3.9"
Requires-Dist: cattrs (<1.1.0,>=1.0) ; python_version <= "3.6"
Requires-Dist: cached-property (~=1.5) ; python_version <= "3.7"
Requires-Dist: cattrs (!=1.7.*,~=1.1) ; python_version > "3.6"
Provides-Extra: airbyte
Requires-Dist: apache-airflow-providers-airbyte ; extra == 'airbyte'
Provides-Extra: alibaba
Requires-Dist: apache-airflow-providers-alibaba ; extra == 'alibaba'
Provides-Extra: all
Requires-Dist: JIRA (>1.0.7) ; extra == 'all'
Requires-Dist: PyOpenSSL ; extra == 'all'
Requires-Dist: amqp ; extra == 'all'
Requires-Dist: analytics-python (>=1.2.9) ; extra == 'all'
Requires-Dist: apache-airflow-providers-http ; extra == 'all'
Requires-Dist: apache-beam (>=2.20.0) ; extra == 'all'
Requires-Dist: arrow (>=0.16.0) ; extra == 'all'
Requires-Dist: asana (>=0.10) ; extra == 'all'
Requires-Dist: atlasclient (>=0.1.2) ; extra == 'all'
Requires-Dist: authlib ; extra == 'all'
Requires-Dist: azure-batch (>=8.0.0) ; extra == 'all'
Requires-Dist: azure-cosmos (>=4.0.0) ; extra == 'all'
Requires-Dist: azure-datalake-store (>=0.0.45) ; extra == 'all'
Requires-Dist: azure-identity (>=1.3.1) ; extra == 'all'
Requires-Dist: azure-keyvault (>=4.1.0) ; extra == 'all'
Requires-Dist: azure-kusto-data (<0.1,>=0.0.43) ; extra == 'all'
Requires-Dist: azure-mgmt-containerinstance (<2.0,>=1.5.0) ; extra == 'all'
Requires-Dist: azure-mgmt-datafactory (<2.0,>=1.0.0) ; extra == 'all'
Requires-Dist: azure-mgmt-datalake-store (>=0.5.0) ; extra == 'all'
Requires-Dist: azure-mgmt-resource (>=2.2.0) ; extra == 'all'
Requires-Dist: azure-storage-blob (<12.9.0,>=12.7.0) ; extra == 'all'
Requires-Dist: azure-storage-common (>=2.1.0) ; extra == 'all'
Requires-Dist: azure-storage-file (>=2.1.0) ; extra == 'all'
Requires-Dist: bcrypt (>=2.0.0) ; extra == 'all'
Requires-Dist: blinker (>=1.1) ; extra == 'all'
Requires-Dist: boto3 (>=1.15.0) ; extra == 'all'
Requires-Dist: cassandra-driver (>=3.13.0) ; extra == 'all'
Requires-Dist: cgroupspy (>0.1.4) ; extra == 'all'
Requires-Dist: cloudant (>=2.0) ; extra == 'all'
Requires-Dist: cloudpickle (>=1.4.1) ; extra == 'all'
Requires-Dist: cryptography (>=2.0.0) ; extra == 'all'
Requires-Dist: cx-Oracle (>=5.1.2) ; extra == 'all'
Requires-Dist: dask (>=2.9.0) ; extra == 'all'
Requires-Dist: databricks-sql-connector (<2.0.0,>=1.0.0) ; extra == 'all'
Requires-Dist: datadog (>=0.14.0) ; extra == 'all'
Requires-Dist: distributed (>=2.11.1) ; extra == 'all'
Requires-Dist: dnspython (>=1.13.0) ; extra == 'all'
Requires-Dist: docker (>=5.0.3) ; extra == 'all'
Requires-Dist: elasticsearch-dbapi ; extra == 'all'
Requires-Dist: elasticsearch-dsl (>=5.0.0) ; extra == 'all'
Requires-Dist: elasticsearch (>7) ; extra == 'all'
Requires-Dist: eventlet (>=0.9.7) ; extra == 'all'
Requires-Dist: facebook-business (>=6.0.2) ; extra == 'all'
Requires-Dist: flask-bcrypt (>=0.7.1) ; extra == 'all'
Requires-Dist: flower (>=1.0.0) ; extra == 'all'
Requires-Dist: gevent (>=0.13) ; extra == 'all'
Requires-Dist: google-ads (<14.0.1,>=12.0.0) ; extra == 'all'
Requires-Dist: google-api-core (<3.0.0,>=1.25.1) ; extra == 'all'
Requires-Dist: google-api-python-client (<2.0.0,>=1.6.0) ; extra == 'all'
Requires-Dist: google-auth-httplib2 (>=0.0.1) ; extra == 'all'
Requires-Dist: google-auth (>=1.0.0) ; extra == 'all'
Requires-Dist: google-auth (<3.0.0,>=1.0.0) ; extra == 'all'
Requires-Dist: google-cloud-aiplatform (<2.0.0,>=1.7.1) ; extra == 'all'
Requires-Dist: google-cloud-automl (>=2.1.0) ; extra == 'all'
Requires-Dist: google-cloud-bigquery-datatransfer (>=3.0.0) ; extra == 'all'
Requires-Dist: google-cloud-bigtable (<2.0.0,>=1.0.0) ; extra == 'all'
Requires-Dist: google-cloud-build (>=3.0.0) ; extra == 'all'
Requires-Dist: google-cloud-container (<2.0.0,>=0.1.1) ; extra == 'all'
Requires-Dist: google-cloud-datacatalog (>=3.0.0) ; extra == 'all'
Requires-Dist: google-cloud-dataplex (>=0.1.0) ; extra == 'all'
Requires-Dist: google-cloud-dataproc-metastore (<2.0.0,>=1.2.0) ; extra == 'all'
Requires-Dist: google-cloud-dataproc (>=3.1.0) ; extra == 'all'
Requires-Dist: google-cloud-dlp (<2.0.0,>=0.11.0) ; extra == 'all'
Requires-Dist: google-cloud-kms (>=2.0.0) ; extra == 'all'
Requires-Dist: google-cloud-language (<2.0.0,>=1.1.1) ; extra == 'all'
Requires-Dist: google-cloud-logging (>=2.1.1) ; extra == 'all'
Requires-Dist: google-cloud-memcache (>=0.2.0) ; extra == 'all'
Requires-Dist: google-cloud-monitoring (>=2.0.0) ; extra == 'all'
Requires-Dist: google-cloud-orchestration-airflow (<2.0.0,>=1.0.0) ; extra == 'all'
Requires-Dist: google-cloud-os-login (>=2.0.0) ; extra == 'all'
Requires-Dist: google-cloud-pubsub (>=2.0.0) ; extra == 'all'
Requires-Dist: google-cloud-redis (>=2.0.0) ; extra == 'all'
Requires-Dist: google-cloud-secret-manager (<2.0.0,>=0.2.0) ; extra == 'all'
Requires-Dist: google-cloud-spanner (<2.0.0,>=1.10.0) ; extra == 'all'
Requires-Dist: google-cloud-speech (<2.0.0,>=0.36.3) ; extra == 'all'
Requires-Dist: google-cloud-storage (<2.0.0,>=1.30) ; extra == 'all'
Requires-Dist: google-cloud-tasks (>=2.0.0) ; extra == 'all'
Requires-Dist: google-cloud-texttospeech (<2.0.0,>=0.4.0) ; extra == 'all'
Requires-Dist: google-cloud-translate (<2.0.0,>=1.5.0) ; extra == 'all'
Requires-Dist: google-cloud-videointelligence (<2.0.0,>=1.7.0) ; extra == 'all'
Requires-Dist: google-cloud-vision (<2.0.0,>=0.35.2) ; extra == 'all'
Requires-Dist: google-cloud-workflows (<2.0.0,>=0.1.0) ; extra == 'all'
Requires-Dist: greenlet (>=0.4.9) ; extra == 'all'
Requires-Dist: grpcio-gcp (>=0.2.2) ; extra == 'all'
Requires-Dist: grpcio (>=1.15.0) ; extra == 'all'
Requires-Dist: hdfs[avro,dataframe,kerberos] (>=2.0.4) ; extra == 'all'
Requires-Dist: hmsclient (>=0.1.0) ; extra == 'all'
Requires-Dist: httpx ; extra == 'all'
Requires-Dist: hvac (>=0.10) ; extra == 'all'
Requires-Dist: influxdb-client (>=1.19.0) ; extra == 'all'
Requires-Dist: jaydebeapi (>=1.1.1) ; extra == 'all'
Requires-Dist: json-merge-patch (>=0.2) ; extra == 'all'
Requires-Dist: jsonpath-ng (>=1.5.3) ; extra == 'all'
Requires-Dist: kubernetes (<12.0.0,>=3.0.0) ; extra == 'all'
Requires-Dist: kylinpy (>=2.6) ; extra == 'all'
Requires-Dist: ldap3 (>=2.5.1) ; extra == 'all'
Requires-Dist: mypy-boto3-rds (>=1.21.0) ; extra == 'all'
Requires-Dist: mypy-boto3-redshift-data (>=1.21.0) ; extra == 'all'
Requires-Dist: neo4j (>=4.2.1) ; extra == 'all'
Requires-Dist: opsgenie-sdk (>=2.1.5) ; extra == 'all'
Requires-Dist: oss2 (>=2.14.0) ; extra == 'all'
Requires-Dist: pandas-gbq (<0.15.0) ; extra == 'all'
Requires-Dist: pandas (<1.4,>=0.17.1) ; extra == 'all'
Requires-Dist: papermill[all] (>=1.2.1) ; extra == 'all'
Requires-Dist: paramiko (>=2.6.0) ; extra == 'all'
Requires-Dist: pdpyras (>=4.1.2) ; extra == 'all'
Requires-Dist: pinotdb (>0.1.2) ; extra == 'all'
Requires-Dist: presto-python-client (<0.8,>=0.7.0) ; extra == 'all'
Requires-Dist: psycopg2-binary (>=2.7.4) ; extra == 'all'
Requires-Dist: pydruid (>=0.4.1) ; extra == 'all'
Requires-Dist: pyexasol (>=0.5.1) ; extra == 'all'
Requires-Dist: pygithub ; extra == 'all'
Requires-Dist: pyhive[hive] (>=0.6.0) ; extra == 'all'
Requires-Dist: pykerberos (>=1.1.13) ; extra == 'all'
Requires-Dist: pymongo (<4.0.0,>=3.6.0) ; extra == 'all'
Requires-Dist: pyodbc ; extra == 'all'
Requires-Dist: pypsrp (>=0.8) ; extra == 'all'
Requires-Dist: pysftp (>=0.2.9) ; extra == 'all'
Requires-Dist: pyspark ; extra == 'all'
Requires-Dist: python-jenkins (>=1.0.0) ; extra == 'all'
Requires-Dist: python-ldap ; extra == 'all'
Requires-Dist: python-telegram-bot (>=13.0) ; extra == 'all'
Requires-Dist: pywinrm (>=0.4) ; extra == 'all'
Requires-Dist: qds-sdk (>=1.10.4) ; extra == 'all'
Requires-Dist: redis (~=3.2) ; extra == 'all'
Requires-Dist: redshift-connector (>=2.0.888) ; extra == 'all'
Requires-Dist: requests (>=2.26.0) ; extra == 'all'
Requires-Dist: requests (<3,>=2.26.0) ; extra == 'all'
Requires-Dist: requests-kerberos (>=0.10.0) ; extra == 'all'
Requires-Dist: scrapbook[all] ; extra == 'all'
Requires-Dist: sendgrid (>=6.0.0) ; extra == 'all'
Requires-Dist: sentry-sdk (>=0.8.0) ; extra == 'all'
Requires-Dist: simple-salesforce (>=1.0.0) ; extra == 'all'
Requires-Dist: slack-sdk (>=3.0.0) ; extra == 'all'
Requires-Dist: smbprotocol (>=1.5.0) ; extra == 'all'
Requires-Dist: snakebite-py3 ; extra == 'all'
Requires-Dist: snowflake-connector-python (>=2.4.1) ; extra == 'all'
Requires-Dist: snowflake-sqlalchemy (!=1.2.5,>=1.1.0) ; extra == 'all'
Requires-Dist: spython (>=0.0.56) ; extra == 'all'
Requires-Dist: sqlalchemy-bigquery (>=1.2.1) ; extra == 'all'
Requires-Dist: sqlalchemy-drill (>=1.1.0) ; extra == 'all'
Requires-Dist: sqlalchemy-redshift (>=0.8.6) ; extra == 'all'
Requires-Dist: sqlparse (>=0.4.1) ; extra == 'all'
Requires-Dist: sshtunnel (>=0.3.2) ; extra == 'all'
Requires-Dist: statsd (>=3.3.0) ; extra == 'all'
Requires-Dist: tableauserverclient ; extra == 'all'
Requires-Dist: thrift (>=0.9.2) ; extra == 'all'
Requires-Dist: thrift-sasl (>=0.2.0) ; extra == 'all'
Requires-Dist: trino (>=0.301.0) ; extra == 'all'
Requires-Dist: vertica-python (>=0.5.1) ; extra == 'all'
Requires-Dist: virtualenv ; extra == 'all'
Requires-Dist: watchtower (~=2.0.1) ; extra == 'all'
Requires-Dist: yandexcloud (>=0.146.0) ; extra == 'all'
Requires-Dist: zenpy (>=2.0.24) ; extra == 'all'
Requires-Dist: apache-airflow-providers-airbyte ; extra == 'all'
Requires-Dist: apache-airflow-providers-alibaba ; extra == 'all'
Requires-Dist: apache-airflow-providers-amazon ; extra == 'all'
Requires-Dist: apache-airflow-providers-apache-beam ; extra == 'all'
Requires-Dist: apache-airflow-providers-apache-cassandra ; extra == 'all'
Requires-Dist: apache-airflow-providers-apache-drill ; extra == 'all'
Requires-Dist: apache-airflow-providers-apache-druid ; extra == 'all'
Requires-Dist: apache-airflow-providers-apache-hdfs ; extra == 'all'
Requires-Dist: apache-airflow-providers-apache-hive ; extra == 'all'
Requires-Dist: apache-airflow-providers-apache-kylin ; extra == 'all'
Requires-Dist: apache-airflow-providers-apache-livy ; extra == 'all'
Requires-Dist: apache-airflow-providers-apache-pig ; extra == 'all'
Requires-Dist: apache-airflow-providers-apache-pinot ; extra == 'all'
Requires-Dist: apache-airflow-providers-apache-spark ; extra == 'all'
Requires-Dist: apache-airflow-providers-apache-sqoop ; extra == 'all'
Requires-Dist: apache-airflow-providers-asana ; extra == 'all'
Requires-Dist: apache-airflow-providers-celery ; extra == 'all'
Requires-Dist: apache-airflow-providers-cloudant ; extra == 'all'
Requires-Dist: apache-airflow-providers-cncf-kubernetes ; extra == 'all'
Requires-Dist: apache-airflow-providers-databricks ; extra == 'all'
Requires-Dist: apache-airflow-providers-datadog ; extra == 'all'
Requires-Dist: apache-airflow-providers-dbt-cloud ; extra == 'all'
Requires-Dist: apache-airflow-providers-dingding ; extra == 'all'
Requires-Dist: apache-airflow-providers-discord ; extra == 'all'
Requires-Dist: apache-airflow-providers-docker ; extra == 'all'
Requires-Dist: apache-airflow-providers-elasticsearch ; extra == 'all'
Requires-Dist: apache-airflow-providers-exasol ; extra == 'all'
Requires-Dist: apache-airflow-providers-facebook ; extra == 'all'
Requires-Dist: apache-airflow-providers-ftp ; extra == 'all'
Requires-Dist: apache-airflow-providers-github ; extra == 'all'
Requires-Dist: apache-airflow-providers-google ; extra == 'all'
Requires-Dist: apache-airflow-providers-grpc ; extra == 'all'
Requires-Dist: apache-airflow-providers-hashicorp ; extra == 'all'
Requires-Dist: apache-airflow-providers-imap ; extra == 'all'
Requires-Dist: apache-airflow-providers-influxdb ; extra == 'all'
Requires-Dist: apache-airflow-providers-jdbc ; extra == 'all'
Requires-Dist: apache-airflow-providers-jenkins ; extra == 'all'
Requires-Dist: apache-airflow-providers-jira ; extra == 'all'
Requires-Dist: apache-airflow-providers-microsoft-azure ; extra == 'all'
Requires-Dist: apache-airflow-providers-microsoft-mssql ; extra == 'all'
Requires-Dist: apache-airflow-providers-microsoft-psrp ; extra == 'all'
Requires-Dist: apache-airflow-providers-microsoft-winrm ; extra == 'all'
Requires-Dist: apache-airflow-providers-mongo ; extra == 'all'
Requires-Dist: apache-airflow-providers-mysql ; extra == 'all'
Requires-Dist: apache-airflow-providers-neo4j ; extra == 'all'
Requires-Dist: apache-airflow-providers-odbc ; extra == 'all'
Requires-Dist: apache-airflow-providers-openfaas ; extra == 'all'
Requires-Dist: apache-airflow-providers-opsgenie ; extra == 'all'
Requires-Dist: apache-airflow-providers-oracle ; extra == 'all'
Requires-Dist: apache-airflow-providers-pagerduty ; extra == 'all'
Requires-Dist: apache-airflow-providers-papermill ; extra == 'all'
Requires-Dist: apache-airflow-providers-plexus ; extra == 'all'
Requires-Dist: apache-airflow-providers-postgres ; extra == 'all'
Requires-Dist: apache-airflow-providers-presto ; extra == 'all'
Requires-Dist: apache-airflow-providers-qubole ; extra == 'all'
Requires-Dist: apache-airflow-providers-redis ; extra == 'all'
Requires-Dist: apache-airflow-providers-salesforce ; extra == 'all'
Requires-Dist: apache-airflow-providers-samba ; extra == 'all'
Requires-Dist: apache-airflow-providers-segment ; extra == 'all'
Requires-Dist: apache-airflow-providers-sendgrid ; extra == 'all'
Requires-Dist: apache-airflow-providers-sftp ; extra == 'all'
Requires-Dist: apache-airflow-providers-singularity ; extra == 'all'
Requires-Dist: apache-airflow-providers-slack ; extra == 'all'
Requires-Dist: apache-airflow-providers-snowflake ; extra == 'all'
Requires-Dist: apache-airflow-providers-sqlite ; extra == 'all'
Requires-Dist: apache-airflow-providers-ssh ; extra == 'all'
Requires-Dist: apache-airflow-providers-tableau ; extra == 'all'
Requires-Dist: apache-airflow-providers-telegram ; extra == 'all'
Requires-Dist: apache-airflow-providers-trino ; extra == 'all'
Requires-Dist: apache-airflow-providers-vertica ; extra == 'all'
Requires-Dist: apache-airflow-providers-yandex ; extra == 'all'
Requires-Dist: apache-airflow-providers-zendesk ; extra == 'all'
Requires-Dist: mysql-connector-python (>=8.0.11) ; (platform_machine != "aarch64") and extra == 'all'
Requires-Dist: mysqlclient (>=1.3.6) ; (platform_machine != "aarch64") and extra == 'all'
Requires-Dist: plyvel ; (platform_machine != "aarch64") and extra == 'all'
Requires-Dist: pymssql (>=2.1.5) ; (platform_machine != "aarch64") and extra == 'all'
Requires-Dist: celery (>=5.1.2,~=5.1) ; (python_version < "3.7") and extra == 'all'
Requires-Dist: celery (>=5.2.3) ; (python_version >= "3.7") and extra == 'all'
Requires-Dist: looker-sdk (>=22.2.0) ; (python_version >= "3.7") and extra == 'all'
Requires-Dist: sasl (>=0.3.1) ; (python_version >= "3.9") and extra == 'all'
Provides-Extra: all_dbs
Requires-Dist: cassandra-driver (>=3.13.0) ; extra == 'all_dbs'
Requires-Dist: cloudant (>=2.0) ; extra == 'all_dbs'
Requires-Dist: databricks-sql-connector (<2.0.0,>=1.0.0) ; extra == 'all_dbs'
Requires-Dist: dnspython (>=1.13.0) ; extra == 'all_dbs'
Requires-Dist: hdfs[avro,dataframe,kerberos] (>=2.0.4) ; extra == 'all_dbs'
Requires-Dist: hmsclient (>=0.1.0) ; extra == 'all_dbs'
Requires-Dist: influxdb-client (>=1.19.0) ; extra == 'all_dbs'
Requires-Dist: neo4j (>=4.2.1) ; extra == 'all_dbs'
Requires-Dist: pandas (<1.4,>=0.17.1) ; extra == 'all_dbs'
Requires-Dist: pinotdb (>0.1.2) ; extra == 'all_dbs'
Requires-Dist: presto-python-client (<0.8,>=0.7.0) ; extra == 'all_dbs'
Requires-Dist: psycopg2-binary (>=2.7.4) ; extra == 'all_dbs'
Requires-Dist: pydruid (>=0.4.1) ; extra == 'all_dbs'
Requires-Dist: pyexasol (>=0.5.1) ; extra == 'all_dbs'
Requires-Dist: pyhive[hive] (>=0.6.0) ; extra == 'all_dbs'
Requires-Dist: pymongo (<4.0.0,>=3.6.0) ; extra == 'all_dbs'
Requires-Dist: requests (<3,>=2.26.0) ; extra == 'all_dbs'
Requires-Dist: snakebite-py3 ; extra == 'all_dbs'
Requires-Dist: sqlalchemy-drill (>=1.1.0) ; extra == 'all_dbs'
Requires-Dist: sqlparse (>=0.4.1) ; extra == 'all_dbs'
Requires-Dist: thrift (>=0.9.2) ; extra == 'all_dbs'
Requires-Dist: trino (>=0.301.0) ; extra == 'all_dbs'
Requires-Dist: vertica-python (>=0.5.1) ; extra == 'all_dbs'
Requires-Dist: apache-airflow-providers-apache-cassandra ; extra == 'all_dbs'
Requires-Dist: apache-airflow-providers-apache-drill ; extra == 'all_dbs'
Requires-Dist: apache-airflow-providers-apache-druid ; extra == 'all_dbs'
Requires-Dist: apache-airflow-providers-apache-hdfs ; extra == 'all_dbs'
Requires-Dist: apache-airflow-providers-apache-hive ; extra == 'all_dbs'
Requires-Dist: apache-airflow-providers-apache-pinot ; extra == 'all_dbs'
Requires-Dist: apache-airflow-providers-cloudant ; extra == 'all_dbs'
Requires-Dist: apache-airflow-providers-databricks ; extra == 'all_dbs'
Requires-Dist: apache-airflow-providers-exasol ; extra == 'all_dbs'
Requires-Dist: apache-airflow-providers-influxdb ; extra == 'all_dbs'
Requires-Dist: apache-airflow-providers-microsoft-mssql ; extra == 'all_dbs'
Requires-Dist: apache-airflow-providers-mongo ; extra == 'all_dbs'
Requires-Dist: apache-airflow-providers-mysql ; extra == 'all_dbs'
Requires-Dist: apache-airflow-providers-neo4j ; extra == 'all_dbs'
Requires-Dist: apache-airflow-providers-postgres ; extra == 'all_dbs'
Requires-Dist: apache-airflow-providers-presto ; extra == 'all_dbs'
Requires-Dist: apache-airflow-providers-trino ; extra == 'all_dbs'
Requires-Dist: apache-airflow-providers-vertica ; extra == 'all_dbs'
Requires-Dist: mysql-connector-python (>=8.0.11) ; (platform_machine != "aarch64") and extra == 'all_dbs'
Requires-Dist: mysqlclient (>=1.3.6) ; (platform_machine != "aarch64") and extra == 'all_dbs'
Requires-Dist: pymssql (>=2.1.5) ; (platform_machine != "aarch64") and extra == 'all_dbs'
Requires-Dist: sasl (>=0.3.1) ; (python_version >= "3.9") and extra == 'all_dbs'
Provides-Extra: amazon
Requires-Dist: apache-airflow-providers-amazon ; extra == 'amazon'
Provides-Extra: apache.atlas
Requires-Dist: atlasclient (>=0.1.2) ; extra == 'apache.atlas'
Provides-Extra: apache.beam
Requires-Dist: apache-airflow-providers-apache-beam ; extra == 'apache.beam'
Provides-Extra: apache.cassandra
Requires-Dist: apache-airflow-providers-apache-cassandra ; extra == 'apache.cassandra'
Provides-Extra: apache.drill
Requires-Dist: apache-airflow-providers-apache-drill ; extra == 'apache.drill'
Provides-Extra: apache.druid
Requires-Dist: apache-airflow-providers-apache-druid ; extra == 'apache.druid'
Provides-Extra: apache.hdfs
Requires-Dist: apache-airflow-providers-apache-hdfs ; extra == 'apache.hdfs'
Provides-Extra: apache.hive
Requires-Dist: apache-airflow-providers-apache-hive ; extra == 'apache.hive'
Provides-Extra: apache.kylin
Requires-Dist: apache-airflow-providers-apache-kylin ; extra == 'apache.kylin'
Provides-Extra: apache.livy
Requires-Dist: apache-airflow-providers-apache-livy ; extra == 'apache.livy'
Provides-Extra: apache.pig
Requires-Dist: apache-airflow-providers-apache-pig ; extra == 'apache.pig'
Provides-Extra: apache.pinot
Requires-Dist: apache-airflow-providers-apache-pinot ; extra == 'apache.pinot'
Provides-Extra: apache.spark
Requires-Dist: apache-airflow-providers-apache-spark ; extra == 'apache.spark'
Provides-Extra: apache.sqoop
Requires-Dist: apache-airflow-providers-apache-sqoop ; extra == 'apache.sqoop'
Provides-Extra: apache.webhdfs
Requires-Dist: hdfs[avro,dataframe,kerberos] (>=2.0.4) ; extra == 'apache.webhdfs'
Provides-Extra: asana
Requires-Dist: apache-airflow-providers-asana ; extra == 'asana'
Provides-Extra: async
Requires-Dist: eventlet (>=0.9.7) ; extra == 'async'
Requires-Dist: gevent (>=0.13) ; extra == 'async'
Requires-Dist: greenlet (>=0.4.9) ; extra == 'async'
Provides-Extra: atlas
Requires-Dist: apache-airflow-providers-apache-atlas ; extra == 'atlas'
Provides-Extra: aws
Requires-Dist: apache-airflow-providers-amazon ; extra == 'aws'
Provides-Extra: azure
Requires-Dist: apache-airflow-providers-microsoft-azure ; extra == 'azure'
Provides-Extra: cassandra
Requires-Dist: apache-airflow-providers-apache-cassandra ; extra == 'cassandra'
Provides-Extra: celery
Requires-Dist: apache-airflow-providers-celery ; extra == 'celery'
Provides-Extra: cgroups
Requires-Dist: cgroupspy (>0.1.4) ; extra == 'cgroups'
Provides-Extra: cloudant
Requires-Dist: apache-airflow-providers-cloudant ; extra == 'cloudant'
Provides-Extra: cncf.kubernetes
Requires-Dist: apache-airflow-providers-cncf-kubernetes ; extra == 'cncf.kubernetes'
Provides-Extra: crypto
Provides-Extra: dask
Requires-Dist: cloudpickle (>=1.4.1) ; extra == 'dask'
Requires-Dist: dask (>=2.9.0) ; extra == 'dask'
Requires-Dist: distributed (>=2.11.1) ; extra == 'dask'
Provides-Extra: databricks
Requires-Dist: apache-airflow-providers-databricks ; extra == 'databricks'
Provides-Extra: datadog
Requires-Dist: apache-airflow-providers-datadog ; extra == 'datadog'
Provides-Extra: dbt.cloud
Requires-Dist: apache-airflow-providers-dbt-cloud ; extra == 'dbt.cloud'
Provides-Extra: deprecated_api
Requires-Dist: requests (>=2.26.0) ; extra == 'deprecated_api'
Provides-Extra: devel
Requires-Dist: aws-xray-sdk ; extra == 'devel'
Requires-Dist: bcrypt (>=2.0.0) ; extra == 'devel'
Requires-Dist: beautifulsoup4 (>=4.7.1) ; extra == 'devel'
Requires-Dist: black ; extra == 'devel'
Requires-Dist: blinker ; extra == 'devel'
Requires-Dist: bowler ; extra == 'devel'
Requires-Dist: cgroupspy (>0.1.4) ; extra == 'devel'
Requires-Dist: click (>=7.1) ; extra == 'devel'
Requires-Dist: click (<9,>=7.1) ; extra == 'devel'
Requires-Dist: coverage ; extra == 'devel'
Requires-Dist: cryptography (>=2.0.0) ; extra == 'devel'
Requires-Dist: filelock ; extra == 'devel'
Requires-Dist: flake8-colors ; extra == 'devel'
Requires-Dist: flake8 (>=3.6.0) ; extra == 'devel'
Requires-Dist: flaky ; extra == 'devel'
Requires-Dist: flask-bcrypt (>=0.7.1) ; extra == 'devel'
Requires-Dist: freezegun ; extra == 'devel'
Requires-Dist: github3.py (<3.1.0) ; extra == 'devel'
Requires-Dist: gitpython ; extra == 'devel'
Requires-Dist: ipdb ; extra == 'devel'
Requires-Dist: jira ; extra == 'devel'
Requires-Dist: jsondiff ; extra == 'devel'
Requires-Dist: kubernetes (<12.0.0,>=3.0.0) ; extra == 'devel'
Requires-Dist: mongomock ; extra == 'devel'
Requires-Dist: moto (>=2.2.12,~=2.2) ; extra == 'devel'
Requires-Dist: mypy (==0.770) ; extra == 'devel'
Requires-Dist: pandas (<1.4,>=0.17.1) ; extra == 'devel'
Requires-Dist: parameterized ; extra == 'devel'
Requires-Dist: paramiko ; extra == 'devel'
Requires-Dist: pipdeptree ; extra == 'devel'
Requires-Dist: pre-commit ; extra == 'devel'
Requires-Dist: pygithub ; extra == 'devel'
Requires-Dist: pypsrp ; extra == 'devel'
Requires-Dist: pysftp ; extra == 'devel'
Requires-Dist: pytest-asyncio ; extra == 'devel'
Requires-Dist: pytest-cov ; extra == 'devel'
Requires-Dist: pytest-httpx ; extra == 'devel'
Requires-Dist: pytest-instafail ; extra == 'devel'
Requires-Dist: pytest-rerunfailures (~=9.1) ; extra == 'devel'
Requires-Dist: pytest-timeouts ; extra == 'devel'
Requires-Dist: pytest-xdist ; extra == 'devel'
Requires-Dist: pytest (~=6.0) ; extra == 'devel'
Requires-Dist: python-jose ; extra == 'devel'
Requires-Dist: pywinrm ; extra == 'devel'
Requires-Dist: qds-sdk (>=1.9.6) ; extra == 'devel'
Requires-Dist: requests-mock ; extra == 'devel'
Requires-Dist: rich-click ; extra == 'devel'
Requires-Dist: semver ; extra == 'devel'
Requires-Dist: sphinx-airflow-theme ; extra == 'devel'
Requires-Dist: sphinx-argparse (>=0.1.13) ; extra == 'devel'
Requires-Dist: sphinx-autoapi (~=1.8.0) ; extra == 'devel'
Requires-Dist: sphinx-copybutton ; extra == 'devel'
Requires-Dist: sphinx-jinja (~=1.1) ; extra == 'devel'
Requires-Dist: sphinx-rtd-theme (>=0.1.6) ; extra == 'devel'
Requires-Dist: sphinx (<5.0.0,>=4.0.0) ; extra == 'devel'
Requires-Dist: sphinxcontrib-httpdomain (>=1.7.0) ; extra == 'devel'
Requires-Dist: sphinxcontrib-redoc (>=1.6.0) ; extra == 'devel'
Requires-Dist: sphinxcontrib-spelling (~=7.3) ; extra == 'devel'
Requires-Dist: twine ; extra == 'devel'
Requires-Dist: wheel ; extra == 'devel'
Requires-Dist: yamllint ; extra == 'devel'
Requires-Dist: mysql-connector-python (>=8.0.11) ; (platform_machine != "aarch64") and extra == 'devel'
Requires-Dist: mysqlclient (>=1.3.6) ; (platform_machine != "aarch64") and extra == 'devel'
Provides-Extra: devel_all
Requires-Dist: JIRA (>1.0.7) ; extra == 'devel_all'
Requires-Dist: PyOpenSSL ; extra == 'devel_all'
Requires-Dist: amqp ; extra == 'devel_all'
Requires-Dist: analytics-python (>=1.2.9) ; extra == 'devel_all'
Requires-Dist: apache-airflow-providers-http ; extra == 'devel_all'
Requires-Dist: apache-beam (>=2.20.0) ; extra == 'devel_all'
Requires-Dist: arrow (>=0.16.0) ; extra == 'devel_all'
Requires-Dist: asana (>=0.10) ; extra == 'devel_all'
Requires-Dist: atlasclient (>=0.1.2) ; extra == 'devel_all'
Requires-Dist: authlib ; extra == 'devel_all'
Requires-Dist: aws-xray-sdk ; extra == 'devel_all'
Requires-Dist: azure-batch (>=8.0.0) ; extra == 'devel_all'
Requires-Dist: azure-cosmos (>=4.0.0) ; extra == 'devel_all'
Requires-Dist: azure-datalake-store (>=0.0.45) ; extra == 'devel_all'
Requires-Dist: azure-identity (>=1.3.1) ; extra == 'devel_all'
Requires-Dist: azure-keyvault (>=4.1.0) ; extra == 'devel_all'
Requires-Dist: azure-kusto-data (<0.1,>=0.0.43) ; extra == 'devel_all'
Requires-Dist: azure-mgmt-containerinstance (<2.0,>=1.5.0) ; extra == 'devel_all'
Requires-Dist: azure-mgmt-datafactory (<2.0,>=1.0.0) ; extra == 'devel_all'
Requires-Dist: azure-mgmt-datalake-store (>=0.5.0) ; extra == 'devel_all'
Requires-Dist: azure-mgmt-resource (>=2.2.0) ; extra == 'devel_all'
Requires-Dist: azure-storage-blob (<12.9.0,>=12.7.0) ; extra == 'devel_all'
Requires-Dist: azure-storage-common (>=2.1.0) ; extra == 'devel_all'
Requires-Dist: azure-storage-file (>=2.1.0) ; extra == 'devel_all'
Requires-Dist: bcrypt (>=2.0.0) ; extra == 'devel_all'
Requires-Dist: beautifulsoup4 (>=4.7.1) ; extra == 'devel_all'
Requires-Dist: black ; extra == 'devel_all'
Requires-Dist: blinker ; extra == 'devel_all'
Requires-Dist: blinker (>=1.1) ; extra == 'devel_all'
Requires-Dist: boto3 (>=1.15.0) ; extra == 'devel_all'
Requires-Dist: bowler ; extra == 'devel_all'
Requires-Dist: cassandra-driver (>=3.13.0) ; extra == 'devel_all'
Requires-Dist: cgroupspy (>0.1.4) ; extra == 'devel_all'
Requires-Dist: click (>=7.1) ; extra == 'devel_all'
Requires-Dist: click (<9,>=7.1) ; extra == 'devel_all'
Requires-Dist: cloudant (>=2.0) ; extra == 'devel_all'
Requires-Dist: cloudpickle (>=1.4.1) ; extra == 'devel_all'
Requires-Dist: coverage ; extra == 'devel_all'
Requires-Dist: cryptography (>=2.0.0) ; extra == 'devel_all'
Requires-Dist: cx-Oracle (>=5.1.2) ; extra == 'devel_all'
Requires-Dist: dask (>=2.9.0) ; extra == 'devel_all'
Requires-Dist: databricks-sql-connector (<2.0.0,>=1.0.0) ; extra == 'devel_all'
Requires-Dist: datadog (>=0.14.0) ; extra == 'devel_all'
Requires-Dist: distributed (>=2.11.1) ; extra == 'devel_all'
Requires-Dist: dnspython (>=1.13.0) ; extra == 'devel_all'
Requires-Dist: docker (>=5.0.3) ; extra == 'devel_all'
Requires-Dist: elasticsearch-dbapi ; extra == 'devel_all'
Requires-Dist: elasticsearch-dsl (>=5.0.0) ; extra == 'devel_all'
Requires-Dist: elasticsearch (>7) ; extra == 'devel_all'
Requires-Dist: eventlet (>=0.9.7) ; extra == 'devel_all'
Requires-Dist: facebook-business (>=6.0.2) ; extra == 'devel_all'
Requires-Dist: filelock ; extra == 'devel_all'
Requires-Dist: flake8-colors ; extra == 'devel_all'
Requires-Dist: flake8 (>=3.6.0) ; extra == 'devel_all'
Requires-Dist: flaky ; extra == 'devel_all'
Requires-Dist: flask-bcrypt (>=0.7.1) ; extra == 'devel_all'
Requires-Dist: flower (>=1.0.0) ; extra == 'devel_all'
Requires-Dist: freezegun ; extra == 'devel_all'
Requires-Dist: gevent (>=0.13) ; extra == 'devel_all'
Requires-Dist: github3.py (<3.1.0) ; extra == 'devel_all'
Requires-Dist: gitpython ; extra == 'devel_all'
Requires-Dist: google-ads (<14.0.1,>=12.0.0) ; extra == 'devel_all'
Requires-Dist: google-api-core (<3.0.0,>=1.25.1) ; extra == 'devel_all'
Requires-Dist: google-api-python-client (<2.0.0,>=1.6.0) ; extra == 'devel_all'
Requires-Dist: google-auth-httplib2 (>=0.0.1) ; extra == 'devel_all'
Requires-Dist: google-auth (>=1.0.0) ; extra == 'devel_all'
Requires-Dist: google-auth (<3.0.0,>=1.0.0) ; extra == 'devel_all'
Requires-Dist: google-cloud-aiplatform (<2.0.0,>=1.7.1) ; extra == 'devel_all'
Requires-Dist: google-cloud-automl (>=2.1.0) ; extra == 'devel_all'
Requires-Dist: google-cloud-bigquery-datatransfer (>=3.0.0) ; extra == 'devel_all'
Requires-Dist: google-cloud-bigtable (<2.0.0,>=1.0.0) ; extra == 'devel_all'
Requires-Dist: google-cloud-build (>=3.0.0) ; extra == 'devel_all'
Requires-Dist: google-cloud-container (<2.0.0,>=0.1.1) ; extra == 'devel_all'
Requires-Dist: google-cloud-datacatalog (>=3.0.0) ; extra == 'devel_all'
Requires-Dist: google-cloud-dataplex (>=0.1.0) ; extra == 'devel_all'
Requires-Dist: google-cloud-dataproc-metastore (<2.0.0,>=1.2.0) ; extra == 'devel_all'
Requires-Dist: google-cloud-dataproc (>=3.1.0) ; extra == 'devel_all'
Requires-Dist: google-cloud-dlp (<2.0.0,>=0.11.0) ; extra == 'devel_all'
Requires-Dist: google-cloud-kms (>=2.0.0) ; extra == 'devel_all'
Requires-Dist: google-cloud-language (<2.0.0,>=1.1.1) ; extra == 'devel_all'
Requires-Dist: google-cloud-logging (>=2.1.1) ; extra == 'devel_all'
Requires-Dist: google-cloud-memcache (>=0.2.0) ; extra == 'devel_all'
Requires-Dist: google-cloud-monitoring (>=2.0.0) ; extra == 'devel_all'
Requires-Dist: google-cloud-orchestration-airflow (<2.0.0,>=1.0.0) ; extra == 'devel_all'
Requires-Dist: google-cloud-os-login (>=2.0.0) ; extra == 'devel_all'
Requires-Dist: google-cloud-pubsub (>=2.0.0) ; extra == 'devel_all'
Requires-Dist: google-cloud-redis (>=2.0.0) ; extra == 'devel_all'
Requires-Dist: google-cloud-secret-manager (<2.0.0,>=0.2.0) ; extra == 'devel_all'
Requires-Dist: google-cloud-spanner (<2.0.0,>=1.10.0) ; extra == 'devel_all'
Requires-Dist: google-cloud-speech (<2.0.0,>=0.36.3) ; extra == 'devel_all'
Requires-Dist: google-cloud-storage (<2.0.0,>=1.30) ; extra == 'devel_all'
Requires-Dist: google-cloud-tasks (>=2.0.0) ; extra == 'devel_all'
Requires-Dist: google-cloud-texttospeech (<2.0.0,>=0.4.0) ; extra == 'devel_all'
Requires-Dist: google-cloud-translate (<2.0.0,>=1.5.0) ; extra == 'devel_all'
Requires-Dist: google-cloud-videointelligence (<2.0.0,>=1.7.0) ; extra == 'devel_all'
Requires-Dist: google-cloud-vision (<2.0.0,>=0.35.2) ; extra == 'devel_all'
Requires-Dist: google-cloud-workflows (<2.0.0,>=0.1.0) ; extra == 'devel_all'
Requires-Dist: greenlet (>=0.4.9) ; extra == 'devel_all'
Requires-Dist: grpcio-gcp (>=0.2.2) ; extra == 'devel_all'
Requires-Dist: grpcio (>=1.15.0) ; extra == 'devel_all'
Requires-Dist: hdfs[avro,dataframe,kerberos] (>=2.0.4) ; extra == 'devel_all'
Requires-Dist: hmsclient (>=0.1.0) ; extra == 'devel_all'
Requires-Dist: httpx ; extra == 'devel_all'
Requires-Dist: hvac (>=0.10) ; extra == 'devel_all'
Requires-Dist: influxdb-client (>=1.19.0) ; extra == 'devel_all'
Requires-Dist: ipdb ; extra == 'devel_all'
Requires-Dist: jaydebeapi (>=1.1.1) ; extra == 'devel_all'
Requires-Dist: jira ; extra == 'devel_all'
Requires-Dist: json-merge-patch (>=0.2) ; extra == 'devel_all'
Requires-Dist: jsondiff ; extra == 'devel_all'
Requires-Dist: jsonpath-ng (>=1.5.3) ; extra == 'devel_all'
Requires-Dist: kubernetes (<12.0.0,>=3.0.0) ; extra == 'devel_all'
Requires-Dist: kylinpy (>=2.6) ; extra == 'devel_all'
Requires-Dist: ldap3 (>=2.5.1) ; extra == 'devel_all'
Requires-Dist: mongomock ; extra == 'devel_all'
Requires-Dist: moto (>=2.2.12,~=2.2) ; extra == 'devel_all'
Requires-Dist: mypy-boto3-rds (>=1.21.0) ; extra == 'devel_all'
Requires-Dist: mypy-boto3-redshift-data (>=1.21.0) ; extra == 'devel_all'
Requires-Dist: mypy (==0.770) ; extra == 'devel_all'
Requires-Dist: neo4j (>=4.2.1) ; extra == 'devel_all'
Requires-Dist: opsgenie-sdk (>=2.1.5) ; extra == 'devel_all'
Requires-Dist: oss2 (>=2.14.0) ; extra == 'devel_all'
Requires-Dist: pandas-gbq (<0.15.0) ; extra == 'devel_all'
Requires-Dist: pandas (<1.4,>=0.17.1) ; extra == 'devel_all'
Requires-Dist: papermill[all] (>=1.2.1) ; extra == 'devel_all'
Requires-Dist: parameterized ; extra == 'devel_all'
Requires-Dist: paramiko ; extra == 'devel_all'
Requires-Dist: paramiko (>=2.6.0) ; extra == 'devel_all'
Requires-Dist: pdpyras (>=4.1.2) ; extra == 'devel_all'
Requires-Dist: pinotdb (>0.1.2) ; extra == 'devel_all'
Requires-Dist: pipdeptree ; extra == 'devel_all'
Requires-Dist: pre-commit ; extra == 'devel_all'
Requires-Dist: presto-python-client (<0.8,>=0.7.0) ; extra == 'devel_all'
Requires-Dist: psycopg2-binary (>=2.7.4) ; extra == 'devel_all'
Requires-Dist: pydruid (>=0.4.1) ; extra == 'devel_all'
Requires-Dist: pyexasol (>=0.5.1) ; extra == 'devel_all'
Requires-Dist: pygithub ; extra == 'devel_all'
Requires-Dist: pyhive[hive] (>=0.6.0) ; extra == 'devel_all'
Requires-Dist: pykerberos (>=1.1.13) ; extra == 'devel_all'
Requires-Dist: pymongo (<4.0.0,>=3.6.0) ; extra == 'devel_all'
Requires-Dist: pyodbc ; extra == 'devel_all'
Requires-Dist: pypsrp ; extra == 'devel_all'
Requires-Dist: pypsrp (>=0.8) ; extra == 'devel_all'
Requires-Dist: pysftp ; extra == 'devel_all'
Requires-Dist: pysftp (>=0.2.9) ; extra == 'devel_all'
Requires-Dist: pyspark ; extra == 'devel_all'
Requires-Dist: pytest-asyncio ; extra == 'devel_all'
Requires-Dist: pytest-cov ; extra == 'devel_all'
Requires-Dist: pytest-httpx ; extra == 'devel_all'
Requires-Dist: pytest-instafail ; extra == 'devel_all'
Requires-Dist: pytest-rerunfailures (~=9.1) ; extra == 'devel_all'
Requires-Dist: pytest-timeouts ; extra == 'devel_all'
Requires-Dist: pytest-xdist ; extra == 'devel_all'
Requires-Dist: pytest (~=6.0) ; extra == 'devel_all'
Requires-Dist: python-jenkins (>=1.0.0) ; extra == 'devel_all'
Requires-Dist: python-jose ; extra == 'devel_all'
Requires-Dist: python-ldap ; extra == 'devel_all'
Requires-Dist: python-telegram-bot (>=13.0) ; extra == 'devel_all'
Requires-Dist: pywinrm ; extra == 'devel_all'
Requires-Dist: pywinrm (>=0.4) ; extra == 'devel_all'
Requires-Dist: qds-sdk (>=1.10.4) ; extra == 'devel_all'
Requires-Dist: qds-sdk (>=1.9.6) ; extra == 'devel_all'
Requires-Dist: redis (~=3.2) ; extra == 'devel_all'
Requires-Dist: redshift-connector (>=2.0.888) ; extra == 'devel_all'
Requires-Dist: requests (>=2.26.0) ; extra == 'devel_all'
Requires-Dist: requests (<3,>=2.26.0) ; extra == 'devel_all'
Requires-Dist: requests-kerberos (>=0.10.0) ; extra == 'devel_all'
Requires-Dist: requests-mock ; extra == 'devel_all'
Requires-Dist: rich-click ; extra == 'devel_all'
Requires-Dist: scrapbook[all] ; extra == 'devel_all'
Requires-Dist: semver ; extra == 'devel_all'
Requires-Dist: sendgrid (>=6.0.0) ; extra == 'devel_all'
Requires-Dist: sentry-sdk (>=0.8.0) ; extra == 'devel_all'
Requires-Dist: simple-salesforce (>=1.0.0) ; extra == 'devel_all'
Requires-Dist: slack-sdk (>=3.0.0) ; extra == 'devel_all'
Requires-Dist: smbprotocol (>=1.5.0) ; extra == 'devel_all'
Requires-Dist: snowflake-connector-python (>=2.4.1) ; extra == 'devel_all'
Requires-Dist: snowflake-sqlalchemy (!=1.2.5,>=1.1.0) ; extra == 'devel_all'
Requires-Dist: sphinx-airflow-theme ; extra == 'devel_all'
Requires-Dist: sphinx-argparse (>=0.1.13) ; extra == 'devel_all'
Requires-Dist: sphinx-autoapi (~=1.8.0) ; extra == 'devel_all'
Requires-Dist: sphinx-copybutton ; extra == 'devel_all'
Requires-Dist: sphinx-jinja (~=1.1) ; extra == 'devel_all'
Requires-Dist: sphinx-rtd-theme (>=0.1.6) ; extra == 'devel_all'
Requires-Dist: sphinx (<5.0.0,>=4.0.0) ; extra == 'devel_all'
Requires-Dist: sphinxcontrib-httpdomain (>=1.7.0) ; extra == 'devel_all'
Requires-Dist: sphinxcontrib-redoc (>=1.6.0) ; extra == 'devel_all'
Requires-Dist: sphinxcontrib-spelling (~=7.3) ; extra == 'devel_all'
Requires-Dist: spython (>=0.0.56) ; extra == 'devel_all'
Requires-Dist: sqlalchemy-bigquery (>=1.2.1) ; extra == 'devel_all'
Requires-Dist: sqlalchemy-drill (>=1.1.0) ; extra == 'devel_all'
Requires-Dist: sqlalchemy-redshift (>=0.8.6) ; extra == 'devel_all'
Requires-Dist: sqlparse (>=0.4.1) ; extra == 'devel_all'
Requires-Dist: sshtunnel (>=0.3.2) ; extra == 'devel_all'
Requires-Dist: statsd (>=3.3.0) ; extra == 'devel_all'
Requires-Dist: tableauserverclient ; extra == 'devel_all'
Requires-Dist: thrift (>=0.9.2) ; extra == 'devel_all'
Requires-Dist: thrift-sasl (>=0.2.0) ; extra == 'devel_all'
Requires-Dist: trino (>=0.301.0) ; extra == 'devel_all'
Requires-Dist: twine ; extra == 'devel_all'
Requires-Dist: vertica-python (>=0.5.1) ; extra == 'devel_all'
Requires-Dist: virtualenv ; extra == 'devel_all'
Requires-Dist: watchtower (~=2.0.1) ; extra == 'devel_all'
Requires-Dist: wheel ; extra == 'devel_all'
Requires-Dist: yamllint ; extra == 'devel_all'
Requires-Dist: yandexcloud (>=0.146.0) ; extra == 'devel_all'
Requires-Dist: zenpy (>=2.0.24) ; extra == 'devel_all'
Requires-Dist: apache-airflow-providers-airbyte ; extra == 'devel_all'
Requires-Dist: apache-airflow-providers-alibaba ; extra == 'devel_all'
Requires-Dist: apache-airflow-providers-amazon ; extra == 'devel_all'
Requires-Dist: apache-airflow-providers-apache-beam ; extra == 'devel_all'
Requires-Dist: apache-airflow-providers-apache-cassandra ; extra == 'devel_all'
Requires-Dist: apache-airflow-providers-apache-drill ; extra == 'devel_all'
Requires-Dist: apache-airflow-providers-apache-druid ; extra == 'devel_all'
Requires-Dist: apache-airflow-providers-apache-hdfs ; extra == 'devel_all'
Requires-Dist: apache-airflow-providers-apache-hive ; extra == 'devel_all'
Requires-Dist: apache-airflow-providers-apache-kylin ; extra == 'devel_all'
Requires-Dist: apache-airflow-providers-apache-livy ; extra == 'devel_all'
Requires-Dist: apache-airflow-providers-apache-pig ; extra == 'devel_all'
Requires-Dist: apache-airflow-providers-apache-pinot ; extra == 'devel_all'
Requires-Dist: apache-airflow-providers-apache-spark ; extra == 'devel_all'
Requires-Dist: apache-airflow-providers-apache-sqoop ; extra == 'devel_all'
Requires-Dist: apache-airflow-providers-asana ; extra == 'devel_all'
Requires-Dist: apache-airflow-providers-celery ; extra == 'devel_all'
Requires-Dist: apache-airflow-providers-cloudant ; extra == 'devel_all'
Requires-Dist: apache-airflow-providers-cncf-kubernetes ; extra == 'devel_all'
Requires-Dist: apache-airflow-providers-databricks ; extra == 'devel_all'
Requires-Dist: apache-airflow-providers-datadog ; extra == 'devel_all'
Requires-Dist: apache-airflow-providers-dbt-cloud ; extra == 'devel_all'
Requires-Dist: apache-airflow-providers-dingding ; extra == 'devel_all'
Requires-Dist: apache-airflow-providers-discord ; extra == 'devel_all'
Requires-Dist: apache-airflow-providers-docker ; extra == 'devel_all'
Requires-Dist: apache-airflow-providers-elasticsearch ; extra == 'devel_all'
Requires-Dist: apache-airflow-providers-exasol ; extra == 'devel_all'
Requires-Dist: apache-airflow-providers-facebook ; extra == 'devel_all'
Requires-Dist: apache-airflow-providers-ftp ; extra == 'devel_all'
Requires-Dist: apache-airflow-providers-github ; extra == 'devel_all'
Requires-Dist: apache-airflow-providers-google ; extra == 'devel_all'
Requires-Dist: apache-airflow-providers-grpc ; extra == 'devel_all'
Requires-Dist: apache-airflow-providers-hashicorp ; extra == 'devel_all'
Requires-Dist: apache-airflow-providers-imap ; extra == 'devel_all'
Requires-Dist: apache-airflow-providers-influxdb ; extra == 'devel_all'
Requires-Dist: apache-airflow-providers-jdbc ; extra == 'devel_all'
Requires-Dist: apache-airflow-providers-jenkins ; extra == 'devel_all'
Requires-Dist: apache-airflow-providers-jira ; extra == 'devel_all'
Requires-Dist: apache-airflow-providers-microsoft-azure ; extra == 'devel_all'
Requires-Dist: apache-airflow-providers-microsoft-mssql ; extra == 'devel_all'
Requires-Dist: apache-airflow-providers-microsoft-psrp ; extra == 'devel_all'
Requires-Dist: apache-airflow-providers-microsoft-winrm ; extra == 'devel_all'
Requires-Dist: apache-airflow-providers-mongo ; extra == 'devel_all'
Requires-Dist: apache-airflow-providers-mysql ; extra == 'devel_all'
Requires-Dist: apache-airflow-providers-neo4j ; extra == 'devel_all'
Requires-Dist: apache-airflow-providers-odbc ; extra == 'devel_all'
Requires-Dist: apache-airflow-providers-openfaas ; extra == 'devel_all'
Requires-Dist: apache-airflow-providers-opsgenie ; extra == 'devel_all'
Requires-Dist: apache-airflow-providers-oracle ; extra == 'devel_all'
Requires-Dist: apache-airflow-providers-pagerduty ; extra == 'devel_all'
Requires-Dist: apache-airflow-providers-papermill ; extra == 'devel_all'
Requires-Dist: apache-airflow-providers-plexus ; extra == 'devel_all'
Requires-Dist: apache-airflow-providers-postgres ; extra == 'devel_all'
Requires-Dist: apache-airflow-providers-presto ; extra == 'devel_all'
Requires-Dist: apache-airflow-providers-qubole ; extra == 'devel_all'
Requires-Dist: apache-airflow-providers-redis ; extra == 'devel_all'
Requires-Dist: apache-airflow-providers-salesforce ; extra == 'devel_all'
Requires-Dist: apache-airflow-providers-samba ; extra == 'devel_all'
Requires-Dist: apache-airflow-providers-segment ; extra == 'devel_all'
Requires-Dist: apache-airflow-providers-sendgrid ; extra == 'devel_all'
Requires-Dist: apache-airflow-providers-sftp ; extra == 'devel_all'
Requires-Dist: apache-airflow-providers-singularity ; extra == 'devel_all'
Requires-Dist: apache-airflow-providers-slack ; extra == 'devel_all'
Requires-Dist: apache-airflow-providers-snowflake ; extra == 'devel_all'
Requires-Dist: apache-airflow-providers-sqlite ; extra == 'devel_all'
Requires-Dist: apache-airflow-providers-ssh ; extra == 'devel_all'
Requires-Dist: apache-airflow-providers-tableau ; extra == 'devel_all'
Requires-Dist: apache-airflow-providers-telegram ; extra == 'devel_all'
Requires-Dist: apache-airflow-providers-trino ; extra == 'devel_all'
Requires-Dist: apache-airflow-providers-vertica ; extra == 'devel_all'
Requires-Dist: apache-airflow-providers-yandex ; extra == 'devel_all'
Requires-Dist: apache-airflow-providers-zendesk ; extra == 'devel_all'
Requires-Dist: mysql-connector-python (>=8.0.11) ; (platform_machine != "aarch64") and extra == 'devel_all'
Requires-Dist: mysqlclient (>=1.3.6) ; (platform_machine != "aarch64") and extra == 'devel_all'
Requires-Dist: plyvel ; (platform_machine != "aarch64") and extra == 'devel_all'
Requires-Dist: pymssql (>=2.1.5) ; (platform_machine != "aarch64") and extra == 'devel_all'
Requires-Dist: celery (>=5.1.2,~=5.1) ; (python_version < "3.7") and extra == 'devel_all'
Requires-Dist: celery (>=5.2.3) ; (python_version >= "3.7") and extra == 'devel_all'
Requires-Dist: looker-sdk (>=22.2.0) ; (python_version >= "3.7") and extra == 'devel_all'
Requires-Dist: sasl (>=0.3.1) ; (python_version >= "3.9") and extra == 'devel_all'
Provides-Extra: devel_ci
Requires-Dist: JIRA (>1.0.7) ; extra == 'devel_ci'
Requires-Dist: PyOpenSSL ; extra == 'devel_ci'
Requires-Dist: amqp ; extra == 'devel_ci'
Requires-Dist: analytics-python (>=1.2.9) ; extra == 'devel_ci'
Requires-Dist: apache-airflow-providers-http ; extra == 'devel_ci'
Requires-Dist: apache-beam (>=2.20.0) ; extra == 'devel_ci'
Requires-Dist: arrow (>=0.16.0) ; extra == 'devel_ci'
Requires-Dist: asana (>=0.10) ; extra == 'devel_ci'
Requires-Dist: atlasclient (>=0.1.2) ; extra == 'devel_ci'
Requires-Dist: authlib ; extra == 'devel_ci'
Requires-Dist: aws-xray-sdk ; extra == 'devel_ci'
Requires-Dist: azure-batch (>=8.0.0) ; extra == 'devel_ci'
Requires-Dist: azure-cosmos (>=4.0.0) ; extra == 'devel_ci'
Requires-Dist: azure-datalake-store (>=0.0.45) ; extra == 'devel_ci'
Requires-Dist: azure-identity (>=1.3.1) ; extra == 'devel_ci'
Requires-Dist: azure-keyvault (>=4.1.0) ; extra == 'devel_ci'
Requires-Dist: azure-kusto-data (<0.1,>=0.0.43) ; extra == 'devel_ci'
Requires-Dist: azure-mgmt-containerinstance (<2.0,>=1.5.0) ; extra == 'devel_ci'
Requires-Dist: azure-mgmt-datafactory (<2.0,>=1.0.0) ; extra == 'devel_ci'
Requires-Dist: azure-mgmt-datalake-store (>=0.5.0) ; extra == 'devel_ci'
Requires-Dist: azure-mgmt-resource (>=2.2.0) ; extra == 'devel_ci'
Requires-Dist: azure-storage-blob (<12.9.0,>=12.7.0) ; extra == 'devel_ci'
Requires-Dist: azure-storage-common (>=2.1.0) ; extra == 'devel_ci'
Requires-Dist: azure-storage-file (>=2.1.0) ; extra == 'devel_ci'
Requires-Dist: bcrypt (>=2.0.0) ; extra == 'devel_ci'
Requires-Dist: beautifulsoup4 (>=4.7.1) ; extra == 'devel_ci'
Requires-Dist: black ; extra == 'devel_ci'
Requires-Dist: blinker ; extra == 'devel_ci'
Requires-Dist: blinker (>=1.1) ; extra == 'devel_ci'
Requires-Dist: boto3 (>=1.15.0) ; extra == 'devel_ci'
Requires-Dist: bowler ; extra == 'devel_ci'
Requires-Dist: cassandra-driver (>=3.13.0) ; extra == 'devel_ci'
Requires-Dist: cgroupspy (>0.1.4) ; extra == 'devel_ci'
Requires-Dist: click (>=7.1) ; extra == 'devel_ci'
Requires-Dist: click (<9,>=7.1) ; extra == 'devel_ci'
Requires-Dist: cloudant (>=2.0) ; extra == 'devel_ci'
Requires-Dist: cloudpickle (>=1.4.1) ; extra == 'devel_ci'
Requires-Dist: coverage ; extra == 'devel_ci'
Requires-Dist: cryptography (>=2.0.0) ; extra == 'devel_ci'
Requires-Dist: cx-Oracle (>=5.1.2) ; extra == 'devel_ci'
Requires-Dist: dask (>=2.9.0) ; extra == 'devel_ci'
Requires-Dist: databricks-sql-connector (<2.0.0,>=1.0.0) ; extra == 'devel_ci'
Requires-Dist: datadog (>=0.14.0) ; extra == 'devel_ci'
Requires-Dist: distributed (>=2.11.1) ; extra == 'devel_ci'
Requires-Dist: dnspython (>=1.13.0) ; extra == 'devel_ci'
Requires-Dist: docker (>=5.0.3) ; extra == 'devel_ci'
Requires-Dist: elasticsearch-dbapi ; extra == 'devel_ci'
Requires-Dist: elasticsearch-dsl (>=5.0.0) ; extra == 'devel_ci'
Requires-Dist: elasticsearch (>7) ; extra == 'devel_ci'
Requires-Dist: eventlet (>=0.9.7) ; extra == 'devel_ci'
Requires-Dist: facebook-business (>=6.0.2) ; extra == 'devel_ci'
Requires-Dist: filelock ; extra == 'devel_ci'
Requires-Dist: flake8-colors ; extra == 'devel_ci'
Requires-Dist: flake8 (>=3.6.0) ; extra == 'devel_ci'
Requires-Dist: flaky ; extra == 'devel_ci'
Requires-Dist: flask-bcrypt (>=0.7.1) ; extra == 'devel_ci'
Requires-Dist: flower (>=1.0.0) ; extra == 'devel_ci'
Requires-Dist: freezegun ; extra == 'devel_ci'
Requires-Dist: gevent (>=0.13) ; extra == 'devel_ci'
Requires-Dist: github3.py (<3.1.0) ; extra == 'devel_ci'
Requires-Dist: gitpython ; extra == 'devel_ci'
Requires-Dist: google-ads (<14.0.1,>=12.0.0) ; extra == 'devel_ci'
Requires-Dist: google-api-core (<3.0.0,>=1.25.1) ; extra == 'devel_ci'
Requires-Dist: google-api-python-client (<2.0.0,>=1.6.0) ; extra == 'devel_ci'
Requires-Dist: google-auth-httplib2 (>=0.0.1) ; extra == 'devel_ci'
Requires-Dist: google-auth (>=1.0.0) ; extra == 'devel_ci'
Requires-Dist: google-auth (<3.0.0,>=1.0.0) ; extra == 'devel_ci'
Requires-Dist: google-cloud-aiplatform (<2.0.0,>=1.7.1) ; extra == 'devel_ci'
Requires-Dist: google-cloud-automl (>=2.1.0) ; extra == 'devel_ci'
Requires-Dist: google-cloud-bigquery-datatransfer (>=3.0.0) ; extra == 'devel_ci'
Requires-Dist: google-cloud-bigtable (<2.0.0,>=1.0.0) ; extra == 'devel_ci'
Requires-Dist: google-cloud-build (>=3.0.0) ; extra == 'devel_ci'
Requires-Dist: google-cloud-container (<2.0.0,>=0.1.1) ; extra == 'devel_ci'
Requires-Dist: google-cloud-datacatalog (>=3.0.0) ; extra == 'devel_ci'
Requires-Dist: google-cloud-dataplex (>=0.1.0) ; extra == 'devel_ci'
Requires-Dist: google-cloud-dataproc-metastore (<2.0.0,>=1.2.0) ; extra == 'devel_ci'
Requires-Dist: google-cloud-dataproc (>=3.1.0) ; extra == 'devel_ci'
Requires-Dist: google-cloud-dlp (<2.0.0,>=0.11.0) ; extra == 'devel_ci'
Requires-Dist: google-cloud-kms (>=2.0.0) ; extra == 'devel_ci'
Requires-Dist: google-cloud-language (<2.0.0,>=1.1.1) ; extra == 'devel_ci'
Requires-Dist: google-cloud-logging (>=2.1.1) ; extra == 'devel_ci'
Requires-Dist: google-cloud-memcache (>=0.2.0) ; extra == 'devel_ci'
Requires-Dist: google-cloud-monitoring (>=2.0.0) ; extra == 'devel_ci'
Requires-Dist: google-cloud-orchestration-airflow (<2.0.0,>=1.0.0) ; extra == 'devel_ci'
Requires-Dist: google-cloud-os-login (>=2.0.0) ; extra == 'devel_ci'
Requires-Dist: google-cloud-pubsub (>=2.0.0) ; extra == 'devel_ci'
Requires-Dist: google-cloud-redis (>=2.0.0) ; extra == 'devel_ci'
Requires-Dist: google-cloud-secret-manager (<2.0.0,>=0.2.0) ; extra == 'devel_ci'
Requires-Dist: google-cloud-spanner (<2.0.0,>=1.10.0) ; extra == 'devel_ci'
Requires-Dist: google-cloud-speech (<2.0.0,>=0.36.3) ; extra == 'devel_ci'
Requires-Dist: google-cloud-storage (<2.0.0,>=1.30) ; extra == 'devel_ci'
Requires-Dist: google-cloud-tasks (>=2.0.0) ; extra == 'devel_ci'
Requires-Dist: google-cloud-texttospeech (<2.0.0,>=0.4.0) ; extra == 'devel_ci'
Requires-Dist: google-cloud-translate (<2.0.0,>=1.5.0) ; extra == 'devel_ci'
Requires-Dist: google-cloud-videointelligence (<2.0.0,>=1.7.0) ; extra == 'devel_ci'
Requires-Dist: google-cloud-vision (<2.0.0,>=0.35.2) ; extra == 'devel_ci'
Requires-Dist: google-cloud-workflows (<2.0.0,>=0.1.0) ; extra == 'devel_ci'
Requires-Dist: greenlet (>=0.4.9) ; extra == 'devel_ci'
Requires-Dist: grpcio-gcp (>=0.2.2) ; extra == 'devel_ci'
Requires-Dist: grpcio (>=1.15.0) ; extra == 'devel_ci'
Requires-Dist: hdfs[avro,dataframe,kerberos] (>=2.0.4) ; extra == 'devel_ci'
Requires-Dist: hmsclient (>=0.1.0) ; extra == 'devel_ci'
Requires-Dist: httpx ; extra == 'devel_ci'
Requires-Dist: hvac (>=0.10) ; extra == 'devel_ci'
Requires-Dist: influxdb-client (>=1.19.0) ; extra == 'devel_ci'
Requires-Dist: ipdb ; extra == 'devel_ci'
Requires-Dist: jaydebeapi (>=1.1.1) ; extra == 'devel_ci'
Requires-Dist: jira ; extra == 'devel_ci'
Requires-Dist: json-merge-patch (>=0.2) ; extra == 'devel_ci'
Requires-Dist: jsondiff ; extra == 'devel_ci'
Requires-Dist: jsonpath-ng (>=1.5.3) ; extra == 'devel_ci'
Requires-Dist: kubernetes (<12.0.0,>=3.0.0) ; extra == 'devel_ci'
Requires-Dist: kylinpy (>=2.6) ; extra == 'devel_ci'
Requires-Dist: ldap3 (>=2.5.1) ; extra == 'devel_ci'
Requires-Dist: mongomock ; extra == 'devel_ci'
Requires-Dist: moto (>=2.2.12,~=2.2) ; extra == 'devel_ci'
Requires-Dist: mypy-boto3-rds (>=1.21.0) ; extra == 'devel_ci'
Requires-Dist: mypy-boto3-redshift-data (>=1.21.0) ; extra == 'devel_ci'
Requires-Dist: mypy (==0.770) ; extra == 'devel_ci'
Requires-Dist: neo4j (>=4.2.1) ; extra == 'devel_ci'
Requires-Dist: opsgenie-sdk (>=2.1.5) ; extra == 'devel_ci'
Requires-Dist: oss2 (>=2.14.0) ; extra == 'devel_ci'
Requires-Dist: pandas-gbq (<0.15.0) ; extra == 'devel_ci'
Requires-Dist: pandas (<1.4,>=0.17.1) ; extra == 'devel_ci'
Requires-Dist: papermill[all] (>=1.2.1) ; extra == 'devel_ci'
Requires-Dist: parameterized ; extra == 'devel_ci'
Requires-Dist: paramiko ; extra == 'devel_ci'
Requires-Dist: paramiko (>=2.6.0) ; extra == 'devel_ci'
Requires-Dist: pdpyras (>=4.1.2) ; extra == 'devel_ci'
Requires-Dist: pinotdb (>0.1.2) ; extra == 'devel_ci'
Requires-Dist: pipdeptree ; extra == 'devel_ci'
Requires-Dist: pre-commit ; extra == 'devel_ci'
Requires-Dist: presto-python-client (<0.8,>=0.7.0) ; extra == 'devel_ci'
Requires-Dist: psycopg2-binary (>=2.7.4) ; extra == 'devel_ci'
Requires-Dist: pydruid (>=0.4.1) ; extra == 'devel_ci'
Requires-Dist: pyexasol (>=0.5.1) ; extra == 'devel_ci'
Requires-Dist: pygithub ; extra == 'devel_ci'
Requires-Dist: pyhive[hive] (>=0.6.0) ; extra == 'devel_ci'
Requires-Dist: pykerberos (>=1.1.13) ; extra == 'devel_ci'
Requires-Dist: pymongo (<4.0.0,>=3.6.0) ; extra == 'devel_ci'
Requires-Dist: pyodbc ; extra == 'devel_ci'
Requires-Dist: pypsrp ; extra == 'devel_ci'
Requires-Dist: pypsrp (>=0.8) ; extra == 'devel_ci'
Requires-Dist: pysftp ; extra == 'devel_ci'
Requires-Dist: pysftp (>=0.2.9) ; extra == 'devel_ci'
Requires-Dist: pyspark ; extra == 'devel_ci'
Requires-Dist: pytest-asyncio ; extra == 'devel_ci'
Requires-Dist: pytest-cov ; extra == 'devel_ci'
Requires-Dist: pytest-httpx ; extra == 'devel_ci'
Requires-Dist: pytest-instafail ; extra == 'devel_ci'
Requires-Dist: pytest-rerunfailures (~=9.1) ; extra == 'devel_ci'
Requires-Dist: pytest-timeouts ; extra == 'devel_ci'
Requires-Dist: pytest-xdist ; extra == 'devel_ci'
Requires-Dist: pytest (~=6.0) ; extra == 'devel_ci'
Requires-Dist: python-jenkins (>=1.0.0) ; extra == 'devel_ci'
Requires-Dist: python-jose ; extra == 'devel_ci'
Requires-Dist: python-ldap ; extra == 'devel_ci'
Requires-Dist: python-telegram-bot (>=13.0) ; extra == 'devel_ci'
Requires-Dist: pywinrm ; extra == 'devel_ci'
Requires-Dist: pywinrm (>=0.4) ; extra == 'devel_ci'
Requires-Dist: qds-sdk (>=1.10.4) ; extra == 'devel_ci'
Requires-Dist: qds-sdk (>=1.9.6) ; extra == 'devel_ci'
Requires-Dist: redis (~=3.2) ; extra == 'devel_ci'
Requires-Dist: redshift-connector (>=2.0.888) ; extra == 'devel_ci'
Requires-Dist: requests (>=2.26.0) ; extra == 'devel_ci'
Requires-Dist: requests (<3,>=2.26.0) ; extra == 'devel_ci'
Requires-Dist: requests-kerberos (>=0.10.0) ; extra == 'devel_ci'
Requires-Dist: requests-mock ; extra == 'devel_ci'
Requires-Dist: rich-click ; extra == 'devel_ci'
Requires-Dist: scrapbook[all] ; extra == 'devel_ci'
Requires-Dist: semver ; extra == 'devel_ci'
Requires-Dist: sendgrid (>=6.0.0) ; extra == 'devel_ci'
Requires-Dist: sentry-sdk (>=0.8.0) ; extra == 'devel_ci'
Requires-Dist: simple-salesforce (>=1.0.0) ; extra == 'devel_ci'
Requires-Dist: slack-sdk (>=3.0.0) ; extra == 'devel_ci'
Requires-Dist: smbprotocol (>=1.5.0) ; extra == 'devel_ci'
Requires-Dist: snowflake-connector-python (>=2.4.1) ; extra == 'devel_ci'
Requires-Dist: snowflake-sqlalchemy (!=1.2.5,>=1.1.0) ; extra == 'devel_ci'
Requires-Dist: sphinx-airflow-theme ; extra == 'devel_ci'
Requires-Dist: sphinx-argparse (>=0.1.13) ; extra == 'devel_ci'
Requires-Dist: sphinx-autoapi (~=1.8.0) ; extra == 'devel_ci'
Requires-Dist: sphinx-copybutton ; extra == 'devel_ci'
Requires-Dist: sphinx-jinja (~=1.1) ; extra == 'devel_ci'
Requires-Dist: sphinx-rtd-theme (>=0.1.6) ; extra == 'devel_ci'
Requires-Dist: sphinx (<5.0.0,>=4.0.0) ; extra == 'devel_ci'
Requires-Dist: sphinxcontrib-httpdomain (>=1.7.0) ; extra == 'devel_ci'
Requires-Dist: sphinxcontrib-redoc (>=1.6.0) ; extra == 'devel_ci'
Requires-Dist: sphinxcontrib-spelling (~=7.3) ; extra == 'devel_ci'
Requires-Dist: spython (>=0.0.56) ; extra == 'devel_ci'
Requires-Dist: sqlalchemy-bigquery (>=1.2.1) ; extra == 'devel_ci'
Requires-Dist: sqlalchemy-drill (>=1.1.0) ; extra == 'devel_ci'
Requires-Dist: sqlalchemy-redshift (>=0.8.6) ; extra == 'devel_ci'
Requires-Dist: sqlparse (>=0.4.1) ; extra == 'devel_ci'
Requires-Dist: sshtunnel (>=0.3.2) ; extra == 'devel_ci'
Requires-Dist: statsd (>=3.3.0) ; extra == 'devel_ci'
Requires-Dist: tableauserverclient ; extra == 'devel_ci'
Requires-Dist: thrift (>=0.9.2) ; extra == 'devel_ci'
Requires-Dist: thrift-sasl (>=0.2.0) ; extra == 'devel_ci'
Requires-Dist: trino (>=0.301.0) ; extra == 'devel_ci'
Requires-Dist: twine ; extra == 'devel_ci'
Requires-Dist: vertica-python (>=0.5.1) ; extra == 'devel_ci'
Requires-Dist: virtualenv ; extra == 'devel_ci'
Requires-Dist: watchtower (~=2.0.1) ; extra == 'devel_ci'
Requires-Dist: wheel ; extra == 'devel_ci'
Requires-Dist: yamllint ; extra == 'devel_ci'
Requires-Dist: yandexcloud (>=0.146.0) ; extra == 'devel_ci'
Requires-Dist: zenpy (>=2.0.24) ; extra == 'devel_ci'
Requires-Dist: apache-airflow-providers-airbyte ; extra == 'devel_ci'
Requires-Dist: apache-airflow-providers-alibaba ; extra == 'devel_ci'
Requires-Dist: apache-airflow-providers-amazon ; extra == 'devel_ci'
Requires-Dist: apache-airflow-providers-apache-beam ; extra == 'devel_ci'
Requires-Dist: apache-airflow-providers-apache-cassandra ; extra == 'devel_ci'
Requires-Dist: apache-airflow-providers-apache-drill ; extra == 'devel_ci'
Requires-Dist: apache-airflow-providers-apache-druid ; extra == 'devel_ci'
Requires-Dist: apache-airflow-providers-apache-hdfs ; extra == 'devel_ci'
Requires-Dist: apache-airflow-providers-apache-hive ; extra == 'devel_ci'
Requires-Dist: apache-airflow-providers-apache-kylin ; extra == 'devel_ci'
Requires-Dist: apache-airflow-providers-apache-livy ; extra == 'devel_ci'
Requires-Dist: apache-airflow-providers-apache-pig ; extra == 'devel_ci'
Requires-Dist: apache-airflow-providers-apache-pinot ; extra == 'devel_ci'
Requires-Dist: apache-airflow-providers-apache-spark ; extra == 'devel_ci'
Requires-Dist: apache-airflow-providers-apache-sqoop ; extra == 'devel_ci'
Requires-Dist: apache-airflow-providers-asana ; extra == 'devel_ci'
Requires-Dist: apache-airflow-providers-celery ; extra == 'devel_ci'
Requires-Dist: apache-airflow-providers-cloudant ; extra == 'devel_ci'
Requires-Dist: apache-airflow-providers-cncf-kubernetes ; extra == 'devel_ci'
Requires-Dist: apache-airflow-providers-databricks ; extra == 'devel_ci'
Requires-Dist: apache-airflow-providers-datadog ; extra == 'devel_ci'
Requires-Dist: apache-airflow-providers-dbt-cloud ; extra == 'devel_ci'
Requires-Dist: apache-airflow-providers-dingding ; extra == 'devel_ci'
Requires-Dist: apache-airflow-providers-discord ; extra == 'devel_ci'
Requires-Dist: apache-airflow-providers-docker ; extra == 'devel_ci'
Requires-Dist: apache-airflow-providers-elasticsearch ; extra == 'devel_ci'
Requires-Dist: apache-airflow-providers-exasol ; extra == 'devel_ci'
Requires-Dist: apache-airflow-providers-facebook ; extra == 'devel_ci'
Requires-Dist: apache-airflow-providers-ftp ; extra == 'devel_ci'
Requires-Dist: apache-airflow-providers-github ; extra == 'devel_ci'
Requires-Dist: apache-airflow-providers-google ; extra == 'devel_ci'
Requires-Dist: apache-airflow-providers-grpc ; extra == 'devel_ci'
Requires-Dist: apache-airflow-providers-hashicorp ; extra == 'devel_ci'
Requires-Dist: apache-airflow-providers-imap ; extra == 'devel_ci'
Requires-Dist: apache-airflow-providers-influxdb ; extra == 'devel_ci'
Requires-Dist: apache-airflow-providers-jdbc ; extra == 'devel_ci'
Requires-Dist: apache-airflow-providers-jenkins ; extra == 'devel_ci'
Requires-Dist: apache-airflow-providers-jira ; extra == 'devel_ci'
Requires-Dist: apache-airflow-providers-microsoft-azure ; extra == 'devel_ci'
Requires-Dist: apache-airflow-providers-microsoft-mssql ; extra == 'devel_ci'
Requires-Dist: apache-airflow-providers-microsoft-psrp ; extra == 'devel_ci'
Requires-Dist: apache-airflow-providers-microsoft-winrm ; extra == 'devel_ci'
Requires-Dist: apache-airflow-providers-mongo ; extra == 'devel_ci'
Requires-Dist: apache-airflow-providers-mysql ; extra == 'devel_ci'
Requires-Dist: apache-airflow-providers-neo4j ; extra == 'devel_ci'
Requires-Dist: apache-airflow-providers-odbc ; extra == 'devel_ci'
Requires-Dist: apache-airflow-providers-openfaas ; extra == 'devel_ci'
Requires-Dist: apache-airflow-providers-opsgenie ; extra == 'devel_ci'
Requires-Dist: apache-airflow-providers-oracle ; extra == 'devel_ci'
Requires-Dist: apache-airflow-providers-pagerduty ; extra == 'devel_ci'
Requires-Dist: apache-airflow-providers-papermill ; extra == 'devel_ci'
Requires-Dist: apache-airflow-providers-plexus ; extra == 'devel_ci'
Requires-Dist: apache-airflow-providers-postgres ; extra == 'devel_ci'
Requires-Dist: apache-airflow-providers-presto ; extra == 'devel_ci'
Requires-Dist: apache-airflow-providers-qubole ; extra == 'devel_ci'
Requires-Dist: apache-airflow-providers-redis ; extra == 'devel_ci'
Requires-Dist: apache-airflow-providers-salesforce ; extra == 'devel_ci'
Requires-Dist: apache-airflow-providers-samba ; extra == 'devel_ci'
Requires-Dist: apache-airflow-providers-segment ; extra == 'devel_ci'
Requires-Dist: apache-airflow-providers-sendgrid ; extra == 'devel_ci'
Requires-Dist: apache-airflow-providers-sftp ; extra == 'devel_ci'
Requires-Dist: apache-airflow-providers-singularity ; extra == 'devel_ci'
Requires-Dist: apache-airflow-providers-slack ; extra == 'devel_ci'
Requires-Dist: apache-airflow-providers-snowflake ; extra == 'devel_ci'
Requires-Dist: apache-airflow-providers-sqlite ; extra == 'devel_ci'
Requires-Dist: apache-airflow-providers-ssh ; extra == 'devel_ci'
Requires-Dist: apache-airflow-providers-tableau ; extra == 'devel_ci'
Requires-Dist: apache-airflow-providers-telegram ; extra == 'devel_ci'
Requires-Dist: apache-airflow-providers-trino ; extra == 'devel_ci'
Requires-Dist: apache-airflow-providers-vertica ; extra == 'devel_ci'
Requires-Dist: apache-airflow-providers-yandex ; extra == 'devel_ci'
Requires-Dist: apache-airflow-providers-zendesk ; extra == 'devel_ci'
Requires-Dist: mysql-connector-python (>=8.0.11) ; (platform_machine != "aarch64") and extra == 'devel_ci'
Requires-Dist: mysqlclient (>=1.3.6) ; (platform_machine != "aarch64") and extra == 'devel_ci'
Requires-Dist: plyvel ; (platform_machine != "aarch64") and extra == 'devel_ci'
Requires-Dist: pymssql (>=2.1.5) ; (platform_machine != "aarch64") and extra == 'devel_ci'
Requires-Dist: celery (>=5.1.2,~=5.1) ; (python_version < "3.7") and extra == 'devel_ci'
Requires-Dist: celery (>=5.2.3) ; (python_version >= "3.7") and extra == 'devel_ci'
Requires-Dist: looker-sdk (>=22.2.0) ; (python_version >= "3.7") and extra == 'devel_ci'
Requires-Dist: sasl (>=0.3.1) ; (python_version >= "3.9") and extra == 'devel_ci'
Provides-Extra: devel_hadoop
Requires-Dist: aws-xray-sdk ; extra == 'devel_hadoop'
Requires-Dist: bcrypt (>=2.0.0) ; extra == 'devel_hadoop'
Requires-Dist: beautifulsoup4 (>=4.7.1) ; extra == 'devel_hadoop'
Requires-Dist: black ; extra == 'devel_hadoop'
Requires-Dist: blinker ; extra == 'devel_hadoop'
Requires-Dist: bowler ; extra == 'devel_hadoop'
Requires-Dist: cgroupspy (>0.1.4) ; extra == 'devel_hadoop'
Requires-Dist: click (>=7.1) ; extra == 'devel_hadoop'
Requires-Dist: click (<9,>=7.1) ; extra == 'devel_hadoop'
Requires-Dist: coverage ; extra == 'devel_hadoop'
Requires-Dist: cryptography (>=2.0.0) ; extra == 'devel_hadoop'
Requires-Dist: filelock ; extra == 'devel_hadoop'
Requires-Dist: flake8-colors ; extra == 'devel_hadoop'
Requires-Dist: flake8 (>=3.6.0) ; extra == 'devel_hadoop'
Requires-Dist: flaky ; extra == 'devel_hadoop'
Requires-Dist: flask-bcrypt (>=0.7.1) ; extra == 'devel_hadoop'
Requires-Dist: freezegun ; extra == 'devel_hadoop'
Requires-Dist: github3.py (<3.1.0) ; extra == 'devel_hadoop'
Requires-Dist: gitpython ; extra == 'devel_hadoop'
Requires-Dist: hdfs[avro,dataframe,kerberos] (>=2.0.4) ; extra == 'devel_hadoop'
Requires-Dist: hmsclient (>=0.1.0) ; extra == 'devel_hadoop'
Requires-Dist: ipdb ; extra == 'devel_hadoop'
Requires-Dist: jira ; extra == 'devel_hadoop'
Requires-Dist: jsondiff ; extra == 'devel_hadoop'
Requires-Dist: kubernetes (<12.0.0,>=3.0.0) ; extra == 'devel_hadoop'
Requires-Dist: mongomock ; extra == 'devel_hadoop'
Requires-Dist: moto (>=2.2.12,~=2.2) ; extra == 'devel_hadoop'
Requires-Dist: mypy (==0.770) ; extra == 'devel_hadoop'
Requires-Dist: pandas (<1.4,>=0.17.1) ; extra == 'devel_hadoop'
Requires-Dist: parameterized ; extra == 'devel_hadoop'
Requires-Dist: paramiko ; extra == 'devel_hadoop'
Requires-Dist: pipdeptree ; extra == 'devel_hadoop'
Requires-Dist: pre-commit ; extra == 'devel_hadoop'
Requires-Dist: presto-python-client (<0.8,>=0.7.0) ; extra == 'devel_hadoop'
Requires-Dist: pygithub ; extra == 'devel_hadoop'
Requires-Dist: pyhive[hive] (>=0.6.0) ; extra == 'devel_hadoop'
Requires-Dist: pykerberos (>=1.1.13) ; extra == 'devel_hadoop'
Requires-Dist: pypsrp ; extra == 'devel_hadoop'
Requires-Dist: pysftp ; extra == 'devel_hadoop'
Requires-Dist: pytest-asyncio ; extra == 'devel_hadoop'
Requires-Dist: pytest-cov ; extra == 'devel_hadoop'
Requires-Dist: pytest-httpx ; extra == 'devel_hadoop'
Requires-Dist: pytest-instafail ; extra == 'devel_hadoop'
Requires-Dist: pytest-rerunfailures (~=9.1) ; extra == 'devel_hadoop'
Requires-Dist: pytest-timeouts ; extra == 'devel_hadoop'
Requires-Dist: pytest-xdist ; extra == 'devel_hadoop'
Requires-Dist: pytest (~=6.0) ; extra == 'devel_hadoop'
Requires-Dist: python-jose ; extra == 'devel_hadoop'
Requires-Dist: pywinrm ; extra == 'devel_hadoop'
Requires-Dist: qds-sdk (>=1.9.6) ; extra == 'devel_hadoop'
Requires-Dist: requests-kerberos (>=0.10.0) ; extra == 'devel_hadoop'
Requires-Dist: requests-mock ; extra == 'devel_hadoop'
Requires-Dist: rich-click ; extra == 'devel_hadoop'
Requires-Dist: semver ; extra == 'devel_hadoop'
Requires-Dist: snakebite-py3 ; extra == 'devel_hadoop'
Requires-Dist: sphinx-airflow-theme ; extra == 'devel_hadoop'
Requires-Dist: sphinx-argparse (>=0.1.13) ; extra == 'devel_hadoop'
Requires-Dist: sphinx-autoapi (~=1.8.0) ; extra == 'devel_hadoop'
Requires-Dist: sphinx-copybutton ; extra == 'devel_hadoop'
Requires-Dist: sphinx-jinja (~=1.1) ; extra == 'devel_hadoop'
Requires-Dist: sphinx-rtd-theme (>=0.1.6) ; extra == 'devel_hadoop'
Requires-Dist: sphinx (<5.0.0,>=4.0.0) ; extra == 'devel_hadoop'
Requires-Dist: sphinxcontrib-httpdomain (>=1.7.0) ; extra == 'devel_hadoop'
Requires-Dist: sphinxcontrib-redoc (>=1.6.0) ; extra == 'devel_hadoop'
Requires-Dist: sphinxcontrib-spelling (~=7.3) ; extra == 'devel_hadoop'
Requires-Dist: thrift (>=0.9.2) ; extra == 'devel_hadoop'
Requires-Dist: thrift-sasl (>=0.2.0) ; extra == 'devel_hadoop'
Requires-Dist: twine ; extra == 'devel_hadoop'
Requires-Dist: wheel ; extra == 'devel_hadoop'
Requires-Dist: yamllint ; extra == 'devel_hadoop'
Requires-Dist: apache-airflow-providers-apache-hdfs ; extra == 'devel_hadoop'
Requires-Dist: apache-airflow-providers-apache-hive ; extra == 'devel_hadoop'
Requires-Dist: apache-airflow-providers-presto ; extra == 'devel_hadoop'
Requires-Dist: apache-airflow-providers-trino ; extra == 'devel_hadoop'
Requires-Dist: mysql-connector-python (>=8.0.11) ; (platform_machine != "aarch64") and extra == 'devel_hadoop'
Requires-Dist: mysqlclient (>=1.3.6) ; (platform_machine != "aarch64") and extra == 'devel_hadoop'
Requires-Dist: sasl (>=0.3.1) ; (python_version >= "3.9") and extra == 'devel_hadoop'
Provides-Extra: dingding
Requires-Dist: apache-airflow-providers-dingding ; extra == 'dingding'
Provides-Extra: discord
Requires-Dist: apache-airflow-providers-discord ; extra == 'discord'
Provides-Extra: doc
Requires-Dist: click (<9,>=7.1) ; extra == 'doc'
Requires-Dist: sphinx-airflow-theme ; extra == 'doc'
Requires-Dist: sphinx-argparse (>=0.1.13) ; extra == 'doc'
Requires-Dist: sphinx-autoapi (~=1.8.0) ; extra == 'doc'
Requires-Dist: sphinx-copybutton ; extra == 'doc'
Requires-Dist: sphinx-jinja (~=1.1) ; extra == 'doc'
Requires-Dist: sphinx-rtd-theme (>=0.1.6) ; extra == 'doc'
Requires-Dist: sphinx (<5.0.0,>=4.0.0) ; extra == 'doc'
Requires-Dist: sphinxcontrib-httpdomain (>=1.7.0) ; extra == 'doc'
Requires-Dist: sphinxcontrib-redoc (>=1.6.0) ; extra == 'doc'
Requires-Dist: sphinxcontrib-spelling (~=7.3) ; extra == 'doc'
Provides-Extra: docker
Requires-Dist: apache-airflow-providers-docker ; extra == 'docker'
Provides-Extra: druid
Requires-Dist: apache-airflow-providers-apache-druid ; extra == 'druid'
Provides-Extra: elasticsearch
Requires-Dist: apache-airflow-providers-elasticsearch ; extra == 'elasticsearch'
Provides-Extra: exasol
Requires-Dist: apache-airflow-providers-exasol ; extra == 'exasol'
Provides-Extra: facebook
Requires-Dist: apache-airflow-providers-facebook ; extra == 'facebook'
Provides-Extra: ftp
Requires-Dist: apache-airflow-providers-ftp ; extra == 'ftp'
Provides-Extra: gcp
Requires-Dist: apache-airflow-providers-google ; extra == 'gcp'
Provides-Extra: gcp_api
Requires-Dist: apache-airflow-providers-google ; extra == 'gcp_api'
Provides-Extra: github
Requires-Dist: apache-airflow-providers-github ; extra == 'github'
Provides-Extra: github_enterprise
Requires-Dist: authlib ; extra == 'github_enterprise'
Provides-Extra: google
Requires-Dist: apache-airflow-providers-google ; extra == 'google'
Provides-Extra: google_auth
Requires-Dist: authlib ; extra == 'google_auth'
Provides-Extra: grpc
Requires-Dist: apache-airflow-providers-grpc ; extra == 'grpc'
Provides-Extra: hashicorp
Requires-Dist: apache-airflow-providers-hashicorp ; extra == 'hashicorp'
Provides-Extra: hdfs
Requires-Dist: apache-airflow-providers-apache-hdfs ; extra == 'hdfs'
Provides-Extra: hive
Requires-Dist: apache-airflow-providers-apache-hive ; extra == 'hive'
Provides-Extra: http
Requires-Dist: apache-airflow-providers-http ; extra == 'http'
Provides-Extra: imap
Requires-Dist: apache-airflow-providers-imap ; extra == 'imap'
Provides-Extra: influxdb
Requires-Dist: apache-airflow-providers-influxdb ; extra == 'influxdb'
Provides-Extra: jdbc
Requires-Dist: apache-airflow-providers-jdbc ; extra == 'jdbc'
Provides-Extra: jenkins
Requires-Dist: apache-airflow-providers-jenkins ; extra == 'jenkins'
Provides-Extra: jira
Requires-Dist: apache-airflow-providers-jira ; extra == 'jira'
Provides-Extra: kerberos
Requires-Dist: pykerberos (>=1.1.13) ; extra == 'kerberos'
Requires-Dist: requests-kerberos (>=0.10.0) ; extra == 'kerberos'
Requires-Dist: thrift-sasl (>=0.2.0) ; extra == 'kerberos'
Provides-Extra: kubernetes
Requires-Dist: apache-airflow-providers-cncf-kubernetes ; extra == 'kubernetes'
Provides-Extra: ldap
Requires-Dist: ldap3 (>=2.5.1) ; extra == 'ldap'
Requires-Dist: python-ldap ; extra == 'ldap'
Provides-Extra: leveldb
Requires-Dist: plyvel ; (platform_machine != "aarch64") and extra == 'leveldb'
Provides-Extra: microsoft.azure
Requires-Dist: apache-airflow-providers-microsoft-azure ; extra == 'microsoft.azure'
Provides-Extra: microsoft.mssql
Requires-Dist: apache-airflow-providers-microsoft-mssql ; extra == 'microsoft.mssql'
Provides-Extra: microsoft.psrp
Requires-Dist: apache-airflow-providers-microsoft-psrp ; extra == 'microsoft.psrp'
Provides-Extra: microsoft.winrm
Requires-Dist: apache-airflow-providers-microsoft-winrm ; extra == 'microsoft.winrm'
Provides-Extra: mongo
Requires-Dist: apache-airflow-providers-mongo ; extra == 'mongo'
Provides-Extra: mssql
Requires-Dist: apache-airflow-providers-microsoft-mssql ; extra == 'mssql'
Provides-Extra: mysql
Requires-Dist: apache-airflow-providers-mysql ; extra == 'mysql'
Provides-Extra: neo4j
Requires-Dist: apache-airflow-providers-neo4j ; extra == 'neo4j'
Provides-Extra: odbc
Requires-Dist: apache-airflow-providers-odbc ; extra == 'odbc'
Provides-Extra: openfaas
Requires-Dist: apache-airflow-providers-openfaas ; extra == 'openfaas'
Provides-Extra: opsgenie
Requires-Dist: apache-airflow-providers-opsgenie ; extra == 'opsgenie'
Provides-Extra: oracle
Requires-Dist: apache-airflow-providers-oracle ; extra == 'oracle'
Provides-Extra: pagerduty
Requires-Dist: apache-airflow-providers-pagerduty ; extra == 'pagerduty'
Provides-Extra: pandas
Requires-Dist: pandas (<1.4,>=0.17.1) ; extra == 'pandas'
Provides-Extra: papermill
Requires-Dist: apache-airflow-providers-papermill ; extra == 'papermill'
Provides-Extra: password
Requires-Dist: bcrypt (>=2.0.0) ; extra == 'password'
Requires-Dist: flask-bcrypt (>=0.7.1) ; extra == 'password'
Provides-Extra: pinot
Requires-Dist: apache-airflow-providers-apache-pinot ; extra == 'pinot'
Provides-Extra: plexus
Requires-Dist: apache-airflow-providers-plexus ; extra == 'plexus'
Provides-Extra: postgres
Requires-Dist: apache-airflow-providers-postgres ; extra == 'postgres'
Provides-Extra: presto
Requires-Dist: apache-airflow-providers-presto ; extra == 'presto'
Provides-Extra: qds
Requires-Dist: apache-airflow-providers-qubole ; extra == 'qds'
Provides-Extra: qubole
Requires-Dist: apache-airflow-providers-qubole ; extra == 'qubole'
Provides-Extra: rabbitmq
Requires-Dist: amqp ; extra == 'rabbitmq'
Provides-Extra: redis
Requires-Dist: apache-airflow-providers-redis ; extra == 'redis'
Provides-Extra: s3
Requires-Dist: apache-airflow-providers-amazon ; extra == 's3'
Provides-Extra: salesforce
Requires-Dist: apache-airflow-providers-salesforce ; extra == 'salesforce'
Provides-Extra: samba
Requires-Dist: apache-airflow-providers-samba ; extra == 'samba'
Provides-Extra: segment
Requires-Dist: apache-airflow-providers-segment ; extra == 'segment'
Provides-Extra: sendgrid
Requires-Dist: apache-airflow-providers-sendgrid ; extra == 'sendgrid'
Provides-Extra: sentry
Requires-Dist: blinker (>=1.1) ; extra == 'sentry'
Requires-Dist: sentry-sdk (>=0.8.0) ; extra == 'sentry'
Provides-Extra: sftp
Requires-Dist: apache-airflow-providers-sftp ; extra == 'sftp'
Provides-Extra: singularity
Requires-Dist: apache-airflow-providers-singularity ; extra == 'singularity'
Provides-Extra: slack
Requires-Dist: apache-airflow-providers-slack ; extra == 'slack'
Provides-Extra: snowflake
Requires-Dist: apache-airflow-providers-snowflake ; extra == 'snowflake'
Provides-Extra: spark
Requires-Dist: apache-airflow-providers-apache-spark ; extra == 'spark'
Provides-Extra: sqlite
Requires-Dist: apache-airflow-providers-sqlite ; extra == 'sqlite'
Provides-Extra: ssh
Requires-Dist: apache-airflow-providers-ssh ; extra == 'ssh'
Provides-Extra: statsd
Requires-Dist: statsd (>=3.3.0) ; extra == 'statsd'
Provides-Extra: tableau
Requires-Dist: apache-airflow-providers-tableau ; extra == 'tableau'
Provides-Extra: telegram
Requires-Dist: apache-airflow-providers-telegram ; extra == 'telegram'
Provides-Extra: trino
Requires-Dist: apache-airflow-providers-trino ; extra == 'trino'
Provides-Extra: vertica
Requires-Dist: apache-airflow-providers-vertica ; extra == 'vertica'
Provides-Extra: virtualenv
Requires-Dist: virtualenv ; extra == 'virtualenv'
Provides-Extra: webhdfs
Requires-Dist: hdfs[avro,dataframe,kerberos] (>=2.0.4) ; extra == 'webhdfs'
Provides-Extra: winrm
Requires-Dist: apache-airflow-providers-microsoft-winrm ; extra == 'winrm'
Provides-Extra: yandex
Requires-Dist: apache-airflow-providers-yandex ; extra == 'yandex'
Provides-Extra: zendesk
Requires-Dist: apache-airflow-providers-zendesk ; extra == 'zendesk'
